{
  "minecraft:recipes/decorations/crafting_table": {
    "criteria": {
      "unlock_right_away": "2024-08-28 02:04:23 +0000"
    },
    "done": true
  },
  "minecraft:adventure/adventuring_time": {
    "criteria": {
      "minecraft:old_growth_pine_taiga": "2024-08-28 04:00:37 +0000",
      "minecraft:taiga": "2024-08-28 04:10:34 +0000",
      "minecraft:cherry_grove": "2024-08-28 03:11:31 +0000",
      "minecraft:sunflower_plains": "2024-08-28 03:09:07 +0000",
      "minecraft:birch_forest": "2024-08-29 01:29:34 +0000",
      "minecraft:savanna_plateau": "2024-08-28 02:36:49 +0000",
      "minecraft:beach": "2024-08-28 03:10:08 +0000",
      "minecraft:stony_peaks": "2024-08-28 02:37:58 +0000",
      "minecraft:lukewarm_ocean": "2024-08-28 03:13:53 +0000",
      "minecraft:river": "2024-08-28 02:12:12 +0000",
      "minecraft:dripstone_caves": "2024-08-28 03:33:55 +0000",
      "minecraft:swamp": "2024-08-28 04:00:28 +0000",
      "minecraft:cold_ocean": "2024-08-29 01:30:35 +0000",
      "minecraft:forest": "2024-08-28 02:04:24 +0000",
      "minecraft:windswept_forest": "2024-08-28 04:21:41 +0000",
      "minecraft:ocean": "2024-08-28 03:13:26 +0000",
      "minecraft:old_growth_spruce_taiga": "2024-08-28 04:01:01 +0000",
      "minecraft:old_growth_birch_forest": "2024-08-28 03:09:20 +0000",
      "minecraft:meadow": "2024-08-28 03:08:25 +0000",
      "minecraft:savanna": "2024-08-28 02:12:41 +0000",
      "minecraft:plains": "2024-08-28 03:08:38 +0000"
    },
    "done": false
  },
  "create:root": {
    "criteria": {
      "0": "2024-08-28 02:06:16 +0000"
    },
    "done": true
  },
  "ae2wtlib:recipes/wireless_universal_terminal/upgrade_pattern_access": {
    "criteria": {
      "has_wit": "2024-08-28 02:06:16 +0000"
    },
    "done": true
  },
  "ae2wtlib:recipes/wireless_universal_terminal/upgrade_crafting": {
    "criteria": {
      "has_wct": "2024-08-28 02:06:16 +0000"
    },
    "done": true
  },
  "ae2wtlib:recipes/wireless_pattern_access_terminal": {
    "criteria": {
      "has_wt": "2024-08-28 02:06:16 +0000"
    },
    "done": true
  },
  "naturescompass:natures_compass_sapling": {
    "criteria": {
      "has_recipe": "2024-08-28 02:06:16 +0000"
    },
    "done": true
  },
  "minecraft:recipes/building_blocks/oak_planks": {
    "criteria": {
      "has_logs": "2024-08-28 02:06:16 +0000"
    },
    "done": true
  },
  "ae2wtlib:recipes/wireless_pattern_encoding_terminal": {
    "criteria": {
      "has_wt": "2024-08-28 02:06:16 +0000"
    },
    "done": true
  },
  "ae2wtlib:recipes/magnet_card": {
    "criteria": {
      "has_wct": "2024-08-28 02:06:16 +0000"
    },
    "done": true
  },
  "naturescompass:natures_compass": {
    "criteria": {
      "has_recipe": "2024-08-28 02:06:16 +0000"
    },
    "done": true
  },
  "domum_ornamentum:recipes/tools/architectscutter": {
    "criteria": {
      "has_log": "2024-08-28 02:06:16 +0000"
    },
    "done": true
  },
  "ae2wtlib:recipes/wireless_universal_terminal/upgrade_pattern_encoding": {
    "criteria": {
      "has_wpt": "2024-08-28 02:06:16 +0000"
    },
    "done": true
  },
  "ae2wtlib:recipes/wireless_universal_terminal/ce": {
    "criteria": {
      "has_wpt": "2024-08-28 02:06:16 +0000",
      "has_wct": "2024-08-28 02:06:16 +0000"
    },
    "done": true
  },
  "ae2wtlib:recipes/wireless_universal_terminal/ca": {
    "criteria": {
      "has_wit": "2024-08-28 02:06:16 +0000",
      "has_wct": "2024-08-28 02:06:16 +0000"
    },
    "done": true
  },
  "ae2wtlib:recipes/wireless_universal_terminal/ae": {
    "criteria": {
      "has_wit": "2024-08-28 02:06:16 +0000",
      "has_wpt": "2024-08-28 02:06:16 +0000"
    },
    "done": true
  },
  "minecraft:recipes/misc/charcoal": {
    "criteria": {
      "has_log": "2024-08-28 02:06:16 +0000"
    },
    "done": true
  },
  "naturescompass:natures_compass_log": {
    "criteria": {
      "has_log": "2024-08-28 02:06:16 +0000"
    },
    "done": true
  },
  "minecraft:recipes/building_blocks/oak_wood": {
    "criteria": {
      "has_log": "2024-08-28 02:06:16 +0000"
    },
    "done": true
  },
  "ae2wtlib:recipes/quantum_bridge_card": {
    "criteria": {
      "has_wit": "2024-08-28 02:06:16 +0000",
      "has_wpt": "2024-08-28 02:06:16 +0000",
      "has_wct": "2024-08-28 02:06:16 +0000"
    },
    "done": true
  },
  "farmersdelight:main/root": {
    "criteria": {
      "seeds": "2024-08-28 02:06:16 +0000"
    },
    "done": true
  },
  "minecraft:recipes/misc/stick": {
    "criteria": {
      "has_planks": "2024-08-28 02:06:45 +0000"
    },
    "done": true
  },
  "minecraft:recipes/building_blocks/oak_slab": {
    "criteria": {
      "has_planks": "2024-08-28 02:06:45 +0000"
    },
    "done": true
  },
  "minecraft:recipes/redstone/oak_door": {
    "criteria": {
      "has_planks": "2024-08-28 02:06:45 +0000"
    },
    "done": true
  },
  "minecraft:recipes/redstone/oak_trapdoor": {
    "criteria": {
      "has_planks": "2024-08-28 02:06:45 +0000"
    },
    "done": true
  },
  "domum_ornamentum:recipes/building_blocks/blockbarreldeco_onside": {
    "criteria": {
      "has_planks": "2024-08-28 02:06:45 +0000"
    },
    "done": true
  },
  "minecraft:recipes/redstone/oak_pressure_plate": {
    "criteria": {
      "has_planks": "2024-08-28 02:06:45 +0000"
    },
    "done": true
  },
  "domum_ornamentum:recipes/building_blocks/blockbarreldeco_standing": {
    "criteria": {
      "has_planks": "2024-08-28 02:06:45 +0000"
    },
    "done": true
  },
  "minecraft:recipes/decorations/oak_sign": {
    "criteria": {
      "has_planks": "2024-08-28 02:06:45 +0000"
    },
    "done": true
  },
  "minecraft:recipes/redstone/oak_fence_gate": {
    "criteria": {
      "has_planks": "2024-08-28 02:06:45 +0000"
    },
    "done": true
  },
  "minecraft:recipes/decorations/barrel": {
    "criteria": {
      "has_planks": "2024-08-28 02:06:45 +0000"
    },
    "done": true
  },
  "minecraft:recipes/building_blocks/oak_stairs": {
    "criteria": {
      "has_planks": "2024-08-28 02:06:45 +0000"
    },
    "done": true
  },
  "minecraft:recipes/decorations/oak_fence": {
    "criteria": {
      "has_planks": "2024-08-28 02:06:45 +0000"
    },
    "done": true
  },
  "minecraft:recipes/redstone/oak_button": {
    "criteria": {
      "has_planks": "2024-08-28 02:06:45 +0000"
    },
    "done": true
  },
  "create:recipes/building_blocks/oak_window": {
    "criteria": {
      "has_ingredient": "2024-08-28 02:06:45 +0000"
    },
    "done": true
  },
  "create:recipes/misc/crafting/appliances/crafting_blueprint": {
    "criteria": {
      "has_item": "2024-08-28 02:06:49 +0000"
    },
    "done": true
  },
  "minecraft:story/root": {
    "criteria": {
      "crafting_table": "2024-08-28 02:06:49 +0000"
    },
    "done": true
  },
  "minecraft:recipes/decorations/ladder": {
    "criteria": {
      "has_stick": "2024-08-28 02:06:52 +0000"
    },
    "done": true
  },
  "minecraft:recipes/tools/wooden_axe": {
    "criteria": {
      "has_stick": "2024-08-28 02:06:52 +0000"
    },
    "done": true
  },
  "minecraft:recipes/decorations/campfire": {
    "criteria": {
      "has_stick": "2024-08-28 02:06:52 +0000"
    },
    "done": true
  },
  "minecraft:recipes/combat/wooden_sword": {
    "criteria": {
      "has_stick": "2024-08-28 02:06:52 +0000"
    },
    "done": true
  },
  "minecraft:recipes/tools/wooden_pickaxe": {
    "criteria": {
      "has_stick": "2024-08-28 02:06:52 +0000"
    },
    "done": true
  },
  "minecraft:recipes/tools/wooden_hoe": {
    "criteria": {
      "has_stick": "2024-08-28 02:06:52 +0000"
    },
    "done": true
  },
  "spelunkery:recipes/stick": {
    "criteria": {
      "has_item": "2024-08-28 02:06:52 +0000"
    },
    "done": true
  },
  "minecraft:recipes/tools/wooden_shovel": {
    "criteria": {
      "has_stick": "2024-08-28 02:06:52 +0000"
    },
    "done": true
  },
  "ae2:recipes/misc/network/blocks/crank": {
    "criteria": {
      "has_stick": "2024-08-28 02:06:52 +0000"
    },
    "done": true
  },
  "farmersdelight:recipes/combat/flint_knife": {
    "criteria": {
      "has_stick": "2024-08-28 02:06:52 +0000"
    },
    "done": true
  },
  "minecolonies:recipes/misc/shapetool": {
    "criteria": {
      "has_stick": "2024-08-28 02:06:52 +0000"
    },
    "done": true
  },
  "farmersdelight:recipes/decorations/cutting_board": {
    "criteria": {
      "has_stick": "2024-08-28 02:06:52 +0000"
    },
    "done": true
  },
  "minecraft:recipes/transportation/cherry_boat": {
    "criteria": {
      "in_water": "2024-08-28 02:10:07 +0000"
    },
    "done": true
  },
  "minecraft:recipes/transportation/acacia_boat": {
    "criteria": {
      "in_water": "2024-08-28 02:10:07 +0000"
    },
    "done": true
  },
  "minecraft:recipes/transportation/jungle_boat": {
    "criteria": {
      "in_water": "2024-08-28 02:10:07 +0000"
    },
    "done": true
  },
  "minecraft:recipes/transportation/spruce_boat": {
    "criteria": {
      "in_water": "2024-08-28 02:10:07 +0000"
    },
    "done": true
  },
  "minecraft:recipes/transportation/mangrove_boat": {
    "criteria": {
      "in_water": "2024-08-28 02:10:07 +0000"
    },
    "done": true
  },
  "minecraft:recipes/transportation/dark_oak_boat": {
    "criteria": {
      "in_water": "2024-08-28 02:10:07 +0000"
    },
    "done": true
  },
  "minecraft:recipes/transportation/bamboo_raft": {
    "criteria": {
      "in_water": "2024-08-28 02:10:07 +0000"
    },
    "done": true
  },
  "minecraft:recipes/transportation/birch_boat": {
    "criteria": {
      "in_water": "2024-08-28 02:10:07 +0000"
    },
    "done": true
  },
  "minecraft:recipes/transportation/oak_boat": {
    "criteria": {
      "in_water": "2024-08-28 02:10:07 +0000"
    },
    "done": true
  },
  "minecraft:recipes/building_blocks/cobblestone_slab": {
    "criteria": {
      "has_cobblestone": "2024-08-28 02:10:15 +0000"
    },
    "done": true
  },
  "minecraft:recipes/decorations/cobblestone_wall_from_cobblestone_stonecutting": {
    "criteria": {
      "has_cobblestone": "2024-08-28 02:10:15 +0000"
    },
    "done": true
  },
  "minecraft:recipes/building_blocks/cobblestone_stairs": {
    "criteria": {
      "has_cobblestone": "2024-08-28 02:10:15 +0000"
    },
    "done": true
  },
  "minecraft:recipes/redstone/lever": {
    "criteria": {
      "has_cobblestone": "2024-08-28 02:10:15 +0000"
    },
    "done": true
  },
  "minecraft:recipes/combat/stone_sword": {
    "criteria": {
      "has_cobblestone": "2024-08-28 02:10:15 +0000"
    },
    "done": true
  },
  "minecraft:recipes/decorations/cobblestone_wall": {
    "criteria": {
      "has_cobblestone": "2024-08-28 02:10:15 +0000"
    },
    "done": true
  },
  "minecraft:recipes/tools/stone_axe": {
    "criteria": {
      "has_cobblestone": "2024-08-28 02:10:15 +0000"
    },
    "done": true
  },
  "minecraft:story/mine_stone": {
    "criteria": {
      "get_stone": "2024-08-28 02:10:15 +0000"
    },
    "done": true
  },
  "minecraft:recipes/decorations/furnace": {
    "criteria": {
      "has_cobblestone": "2024-08-28 02:10:15 +0000"
    },
    "done": true
  },
  "minecraft:recipes/building_blocks/cobblestone_slab_from_cobblestone_stonecutting": {
    "criteria": {
      "has_cobblestone": "2024-08-28 02:10:15 +0000"
    },
    "done": true
  },
  "minecraft:recipes/building_blocks/stone": {
    "criteria": {
      "has_cobblestone": "2024-08-28 02:10:15 +0000"
    },
    "done": true
  },
  "minecraft:recipes/tools/stone_pickaxe": {
    "criteria": {
      "has_cobblestone": "2024-08-28 02:10:15 +0000"
    },
    "done": true
  },
  "domum_ornamentum:recipes/tools/cobblestone_extra": {
    "criteria": {
      "has_material": "2024-08-28 02:10:15 +0000"
    },
    "done": true
  },
  "minecraft:recipes/tools/stone_shovel": {
    "criteria": {
      "has_cobblestone": "2024-08-28 02:10:15 +0000"
    },
    "done": true
  },
  "domum_ornamentum:recipes/tools/blue_cobblestone_extra": {
    "criteria": {
      "has_material": "2024-08-28 02:10:15 +0000"
    },
    "done": true
  },
  "domum_ornamentum:recipes/tools/green_cobblestone_extra": {
    "criteria": {
      "has_material": "2024-08-28 02:10:15 +0000"
    },
    "done": true
  },
  "minecraft:recipes/building_blocks/cobblestone_stairs_from_cobblestone_stonecutting": {
    "criteria": {
      "has_cobblestone": "2024-08-28 02:10:15 +0000"
    },
    "done": true
  },
  "minecraft:recipes/tools/stone_hoe": {
    "criteria": {
      "has_cobblestone": "2024-08-28 02:10:15 +0000"
    },
    "done": true
  },
  "domum_ornamentum:recipes/tools/purple_cobblestone_extra": {
    "criteria": {
      "has_material": "2024-08-28 02:10:15 +0000"
    },
    "done": true
  },
  "minecraft:story/upgrade_tools": {
    "criteria": {
      "stone_pickaxe": "2024-08-28 02:10:28 +0000"
    },
    "done": true
  },
  "minecraft:recipes/decorations/torch": {
    "criteria": {
      "has_stone_pickaxe": "2024-08-28 02:10:28 +0000"
    },
    "done": true
  },
  "domum_ornamentum:recipes/tools/brick_extra": {
    "criteria": {
      "has_material": "2024-08-28 02:10:49 +0000"
    },
    "done": true
  },
  "domum_ornamentum:recipes/tools/pink_brick_extra": {
    "criteria": {
      "has_material": "2024-08-28 02:10:49 +0000"
    },
    "done": true
  },
  "domum_ornamentum:recipes/tools/roan_stone_bricks": {
    "criteria": {
      "has_item2_domum_ornamentum_roan_stone_bricks": "2024-08-28 02:10:49 +0000",
      "has_item1_domum_ornamentum_roan_stone_bricks": "2024-08-28 02:10:49 +0000"
    },
    "done": true
  },
  "immersive_weathering:recipes/brick": {
    "criteria": {
      "has_copper_block": "2024-08-28 02:10:49 +0000"
    },
    "done": true
  },
  "domum_ornamentum:recipes/tools/purple_brick_extra": {
    "criteria": {
      "has_material": "2024-08-28 02:10:49 +0000"
    },
    "done": true
  },
  "farmersdelight:recipes/decorations/skillet": {
    "criteria": {
      "has_brick": "2024-08-28 02:10:49 +0000"
    },
    "done": true
  },
  "minecraft:recipes/decorations/decorated_pot_simple": {
    "criteria": {
      "has_brick": "2024-08-28 02:10:49 +0000"
    },
    "done": true
  },
  "domum_ornamentum:recipes/tools/white_brick_extra": {
    "criteria": {
      "has_material": "2024-08-28 02:10:49 +0000"
    },
    "done": true
  },
  "domum_ornamentum:recipes/tools/light_blue_brick_extra": {
    "criteria": {
      "has_material": "2024-08-28 02:10:49 +0000"
    },
    "done": true
  },
  "domum_ornamentum:recipes/tools/gray_brick_extra": {
    "criteria": {
      "has_material": "2024-08-28 02:10:49 +0000"
    },
    "done": true
  },
  "domum_ornamentum:recipes/tools/lime_brick_extra": {
    "criteria": {
      "has_material": "2024-08-28 02:10:49 +0000"
    },
    "done": true
  },
  "domum_ornamentum:recipes/tools/red_brick_extra": {
    "criteria": {
      "has_material": "2024-08-28 02:10:49 +0000"
    },
    "done": true
  },
  "domum_ornamentum:recipes/tools/orange_brick_extra": {
    "criteria": {
      "has_material": "2024-08-28 02:10:49 +0000"
    },
    "done": true
  },
  "domum_ornamentum:recipes/tools/yellow_brick_extra": {
    "criteria": {
      "has_material": "2024-08-28 02:10:49 +0000"
    },
    "done": true
  },
  "domum_ornamentum:recipes/tools/light_gray_brick_extra": {
    "criteria": {
      "has_material": "2024-08-28 02:10:49 +0000"
    },
    "done": true
  },
  "domum_ornamentum:recipes/tools/blue_brick_extra": {
    "criteria": {
      "has_material": "2024-08-28 02:10:49 +0000"
    },
    "done": true
  },
  "domum_ornamentum:recipes/tools/green_brick_extra": {
    "criteria": {
      "has_material": "2024-08-28 02:10:49 +0000"
    },
    "done": true
  },
  "domum_ornamentum:recipes/tools/magenta_brick_extra": {
    "criteria": {
      "has_material": "2024-08-28 02:10:49 +0000"
    },
    "done": true
  },
  "minecraft:recipes/building_blocks/bricks": {
    "criteria": {
      "has_brick": "2024-08-28 02:10:49 +0000"
    },
    "done": true
  },
  "domum_ornamentum:recipes/tools/cyan_brick_extra": {
    "criteria": {
      "has_material": "2024-08-28 02:10:49 +0000"
    },
    "done": true
  },
  "domum_ornamentum:recipes/tools/black_brick_extra": {
    "criteria": {
      "has_material": "2024-08-28 02:10:49 +0000"
    },
    "done": true
  },
  "minecraft:adventure/salvage_sherd": {
    "criteria": {
      "has_sherd": "2024-08-28 02:10:49 +0000"
    },
    "done": false
  },
  "domum_ornamentum:recipes/tools/brown_brick_extra": {
    "criteria": {
      "has_material": "2024-08-28 02:10:49 +0000"
    },
    "done": true
  },
  "minecraft:recipes/decorations/flower_pot": {
    "criteria": {
      "has_brick": "2024-08-28 02:10:49 +0000"
    },
    "done": true
  },
  "minecraft:adventure/kill_a_mob": {
    "criteria": {
      "minecraft:zombie": "2024-08-28 02:11:18 +0000"
    },
    "done": true
  },
  "minecraft:adventure/kill_all_mobs": {
    "criteria": {
      "minecraft:pillager": "2024-08-29 01:32:11 +0000",
      "minecraft:skeleton": "2024-08-28 03:38:15 +0000",
      "minecraft:spider": "2024-08-28 03:48:34 +0000",
      "minecraft:slime": "2024-08-28 03:39:49 +0000",
      "minecraft:zombie": "2024-08-28 02:11:18 +0000",
      "minecraft:drowned": "2024-08-29 01:41:56 +0000"
    },
    "done": false
  },
  "minecraft:adventure/root": {
    "criteria": {
      "killed_something": "2024-08-28 02:11:18 +0000"
    },
    "done": true
  },
  "spelunkery:recipes/coal": {
    "criteria": {
      "has_item": "2024-08-28 02:11:21 +0000"
    },
    "done": true
  },
  "minecraft:recipes/building_blocks/coal_block": {
    "criteria": {
      "has_coal": "2024-08-28 02:11:21 +0000"
    },
    "done": true
  },
  "farmersdelight:recipes/cooking/baked_cod_stew": {
    "criteria": {
      "has_any_ingredient": "2024-08-28 02:11:53 +0000"
    },
    "done": true
  },
  "minecraft:recipes/food/baked_potato_from_campfire_cooking": {
    "criteria": {
      "has_potato": "2024-08-28 02:11:53 +0000"
    },
    "done": true
  },
  "minecraft:recipes/food/baked_potato_from_smoking": {
    "criteria": {
      "has_potato": "2024-08-28 02:11:53 +0000"
    },
    "done": true
  },
  "minecraft:recipes/food/baked_potato": {
    "criteria": {
      "has_potato": "2024-08-28 02:11:53 +0000"
    },
    "done": true
  },
  "farmersdelight:recipes/cooking/beef_stew": {
    "criteria": {
      "has_any_ingredient": "2024-08-28 02:11:53 +0000"
    },
    "done": true
  },
  "minecraft:recipes/misc/iron_ingot_from_nuggets": {
    "criteria": {
      "has_iron_nugget": "2024-08-28 02:13:14 +0000"
    },
    "done": true
  },
  "createbigcannons:recipes/misc/shot_balls": {
    "criteria": {
      "has_iron_nugget": "2024-08-28 02:13:14 +0000"
    },
    "done": true
  },
  "immersive_weathering:recipes/iron_nugget": {
    "criteria": {
      "has_copper_block": "2024-08-28 02:13:14 +0000"
    },
    "done": true
  },
  "minecraft:recipes/decorations/lantern": {
    "criteria": {
      "has_iron_nugget": "2024-08-28 02:13:14 +0000"
    },
    "done": true
  },
  "create:recipes/building_blocks/ornate_iron_window": {
    "criteria": {
      "has_ingredient": "2024-08-28 02:13:14 +0000"
    },
    "done": true
  },
  "minecraft:recipes/decorations/chain": {
    "criteria": {
      "has_iron_nugget": "2024-08-28 02:13:14 +0000"
    },
    "done": true
  },
  "createbigcannons:recipes/misc/bag_of_grapeshot": {
    "criteria": {
      "has_iron_nugget": "2024-08-28 02:13:14 +0000"
    },
    "done": true
  },
  "minecraft:recipes/decorations/chest": {
    "criteria": {
      "has_lots_of_items": "2024-08-28 02:13:19 +0000"
    },
    "done": true
  },
  "stoneworks:recipes/building_blocks/mossy_cobbled_andesite_from_andesite_stonecutting": {
    "criteria": {
      "has_andesite": "2024-08-28 02:14:39 +0000"
    },
    "done": true
  },
  "stoneworks:recipes/building_blocks/andesite_tiles_from_andesite_stonecutting": {
    "criteria": {
      "has_andesite": "2024-08-28 02:14:39 +0000"
    },
    "done": true
  },
  "stoneworks:recipes/building_blocks/cobbled_andesite_from_andesite_stonecutting": {
    "criteria": {
      "has_andesite": "2024-08-28 02:14:39 +0000"
    },
    "done": true
  },
  "stoneworks:recipes/building_blocks/andesite_brick_stairs_from_andesite_stonecutting": {
    "criteria": {
      "has_andesite": "2024-08-28 02:14:39 +0000"
    },
    "done": true
  },
  "createbigcannons:recipes/misc/mortar_stone": {
    "criteria": {
      "has_stone": "2024-08-28 02:14:39 +0000"
    },
    "done": true
  },
  "stoneworks:recipes/building_blocks/andesite_paver_slab_from_andesite_stonecutting": {
    "criteria": {
      "has_andesite": "2024-08-28 02:14:39 +0000"
    },
    "done": true
  },
  "stoneworks:recipes/building_blocks/andesite_bricks_from_andesite_stonecutting": {
    "criteria": {
      "has_andesite": "2024-08-28 02:14:39 +0000"
    },
    "done": true
  },
  "stoneworks:recipes/building_blocks/andesite_plate_slab_from_andesite_stonecutting": {
    "criteria": {
      "has_andesite": "2024-08-28 02:14:39 +0000"
    },
    "done": true
  },
  "stoneworks:recipes/building_blocks/mossy_andesite_brick_slab_from_andesite_stonecutting": {
    "criteria": {
      "has_andesite": "2024-08-28 02:14:39 +0000"
    },
    "done": true
  },
  "stoneworks:recipes/building_blocks/andesite_plate_wall_from_andesite_stonecutting": {
    "criteria": {
      "has_andesite": "2024-08-28 02:14:39 +0000"
    },
    "done": true
  },
  "stoneworks:recipes/building_blocks/mossy_andesite_brick_wall_from_andesite_stonecutting": {
    "criteria": {
      "has_andesite": "2024-08-28 02:14:39 +0000"
    },
    "done": true
  },
  "stoneworks:recipes/building_blocks/andesite_tile_slab_from_andesite_stonecutting": {
    "criteria": {
      "has_andesite": "2024-08-28 02:14:39 +0000"
    },
    "done": true
  },
  "create:recipes/building_blocks/andesite_pillar_from_stone_types_andesite_stonecutting": {
    "criteria": {
      "has_stone_types_andesite": "2024-08-28 02:14:39 +0000"
    },
    "done": true
  },
  "create:recipes/building_blocks/polished_cut_andesite_wall_from_stone_types_andesite_stonecutting": {
    "criteria": {
      "has_stone_types_andesite": "2024-08-28 02:14:39 +0000"
    },
    "done": true
  },
  "stoneworks:recipes/building_blocks/cobbled_andesite_wall_from_andesite_stonecutting": {
    "criteria": {
      "has_andesite": "2024-08-28 02:14:39 +0000"
    },
    "done": true
  },
  "stoneworks:recipes/building_blocks/andesite_shingle_wall_from_andesite_stonecutting": {
    "criteria": {
      "has_andesite": "2024-08-28 02:14:39 +0000"
    },
    "done": true
  },
  "minecraft:recipes/building_blocks/andesite_stairs": {
    "criteria": {
      "has_andesite": "2024-08-28 02:14:39 +0000"
    },
    "done": true
  },
  "stoneworks:recipes/building_blocks/cracked_andesite_tiles_from_andesite_stonecutting": {
    "criteria": {
      "has_andesite": "2024-08-28 02:14:39 +0000"
    },
    "done": true
  },
  "create:recipes/building_blocks/cut_andesite_bricks_from_stone_types_andesite_stonecutting": {
    "criteria": {
      "has_stone_types_andesite": "2024-08-28 02:14:39 +0000"
    },
    "done": true
  },
  "create:recipes/building_blocks/small_andesite_bricks_from_stone_types_andesite_stonecutting": {
    "criteria": {
      "has_stone_types_andesite": "2024-08-28 02:14:39 +0000"
    },
    "done": true
  },
  "stoneworks:recipes/building_blocks/cobbled_andesite_slab_from_andesite_stonecutting": {
    "criteria": {
      "has_andesite": "2024-08-28 02:14:39 +0000"
    },
    "done": true
  },
  "stoneworks:recipes/building_blocks/andesite_shingle_stairs_from_andesite_stonecutting": {
    "criteria": {
      "has_andesite": "2024-08-28 02:14:39 +0000"
    },
    "done": true
  },
  "stoneworks:recipes/building_blocks/mossy_cobbled_andesite_stairs_from_andesite_stonecutting": {
    "criteria": {
      "has_andesite": "2024-08-28 02:14:39 +0000"
    },
    "done": true
  },
  "create:recipes/building_blocks/andesite_from_stone_types_andesite_stonecutting": {
    "criteria": {
      "has_stone_types_andesite": "2024-08-28 02:14:39 +0000"
    },
    "done": true
  },
  "minecraft:recipes/building_blocks/polished_andesite_slab_from_andesite_stonecutting": {
    "criteria": {
      "has_andesite": "2024-08-28 02:14:39 +0000"
    },
    "done": true
  },
  "stoneworks:recipes/building_blocks/andesite_paver_wall_from_andesite_stonecutting": {
    "criteria": {
      "has_andesite": "2024-08-28 02:14:39 +0000"
    },
    "done": true
  },
  "create:recipes/building_blocks/cut_andesite_stairs_from_stone_types_andesite_stonecutting": {
    "criteria": {
      "has_stone_types_andesite": "2024-08-28 02:14:39 +0000"
    },
    "done": true
  },
  "minecraft:recipes/decorations/andesite_wall": {
    "criteria": {
      "has_andesite": "2024-08-28 02:14:39 +0000"
    },
    "done": true
  },
  "minecraft:recipes/building_blocks/andesite_slab": {
    "criteria": {
      "has_andesite": "2024-08-28 02:14:39 +0000"
    },
    "done": true
  },
  "stoneworks:recipes/building_blocks/andesite_paver_stairs_from_andesite_stonecutting": {
    "criteria": {
      "has_andesite": "2024-08-28 02:14:39 +0000"
    },
    "done": true
  },
  "create:recipes/building_blocks/polished_cut_andesite_stairs_from_stone_types_andesite_stonecutting": {
    "criteria": {
      "has_stone_types_andesite": "2024-08-28 02:14:40 +0000"
    },
    "done": true
  },
  "stoneworks:recipes/building_blocks/andesite_pavers_from_andesite_stonecutting": {
    "criteria": {
      "has_andesite": "2024-08-28 02:14:40 +0000"
    },
    "done": true
  },
  "create:recipes/building_blocks/small_andesite_brick_stairs_from_stone_types_andesite_stonecutting": {
    "criteria": {
      "has_stone_types_andesite": "2024-08-28 02:14:40 +0000"
    },
    "done": true
  },
  "stoneworks:recipes/building_blocks/andesite_brick_wall_from_andesite_stonecutting": {
    "criteria": {
      "has_andesite": "2024-08-28 02:14:40 +0000"
    },
    "done": true
  },
  "create:recipes/building_blocks/polished_cut_andesite_from_stone_types_andesite_stonecutting": {
    "criteria": {
      "has_stone_types_andesite": "2024-08-28 02:14:40 +0000"
    },
    "done": true
  },
  "minecraft:recipes/building_blocks/polished_andesite_stairs_from_andesite_stonecutting": {
    "criteria": {
      "has_andesite": "2024-08-28 02:14:40 +0000"
    },
    "done": true
  },
  "create:recipes/building_blocks/layered_andesite_from_stone_types_andesite_stonecutting": {
    "criteria": {
      "has_stone_types_andesite": "2024-08-28 02:14:40 +0000"
    },
    "done": true
  },
  "stoneworks:recipes/building_blocks/mossy_cobbled_andesite_slab_from_andesite_stonecutting": {
    "criteria": {
      "has_andesite": "2024-08-28 02:14:40 +0000"
    },
    "done": true
  },
  "stoneworks:recipes/building_blocks/cracked_andesite_bricks_from_andesite_stonecutting": {
    "criteria": {
      "has_andesite": "2024-08-28 02:14:40 +0000"
    },
    "done": true
  },
  "minecraft:recipes/building_blocks/andesite_slab_from_andesite_stonecutting": {
    "criteria": {
      "has_andesite": "2024-08-28 02:14:40 +0000"
    },
    "done": true
  },
  "create:recipes/building_blocks/cut_andesite_brick_wall_from_stone_types_andesite_stonecutting": {
    "criteria": {
      "has_stone_types_andesite": "2024-08-28 02:14:40 +0000"
    },
    "done": true
  },
  "stoneworks:recipes/building_blocks/mossy_andesite_bricks_from_andesite_stonecutting": {
    "criteria": {
      "has_andesite": "2024-08-28 02:14:40 +0000"
    },
    "done": true
  },
  "create:recipes/building_blocks/cut_andesite_brick_stairs_from_stone_types_andesite_stonecutting": {
    "criteria": {
      "has_stone_types_andesite": "2024-08-28 02:14:40 +0000"
    },
    "done": true
  },
  "stoneworks:recipes/building_blocks/andesite_plate_stairs_from_andesite_stonecutting": {
    "criteria": {
      "has_andesite": "2024-08-28 02:14:40 +0000"
    },
    "done": true
  },
  "stoneworks:recipes/building_blocks/andesite_plates_from_andesite_stonecutting": {
    "criteria": {
      "has_andesite": "2024-08-28 02:14:40 +0000"
    },
    "done": true
  },
  "stoneworks:recipes/building_blocks/andesite_shingle_slab_from_andesite_stonecutting": {
    "criteria": {
      "has_andesite": "2024-08-28 02:14:40 +0000"
    },
    "done": true
  },
  "stoneworks:recipes/building_blocks/andesite_pillar_from_andesite_stonecutting": {
    "criteria": {
      "has_andesite": "2024-08-28 02:14:40 +0000"
    },
    "done": true
  },
  "create:recipes/building_blocks/cut_andesite_slab_from_stone_types_andesite_stonecutting": {
    "criteria": {
      "has_stone_types_andesite": "2024-08-28 02:14:40 +0000"
    },
    "done": true
  },
  "create:recipes/building_blocks/small_andesite_brick_slab_from_stone_types_andesite_stonecutting": {
    "criteria": {
      "has_stone_types_andesite": "2024-08-28 02:14:40 +0000"
    },
    "done": true
  },
  "stoneworks:recipes/building_blocks/cobbled_andesite_stairs_from_andesite_stonecutting": {
    "criteria": {
      "has_andesite": "2024-08-28 02:14:40 +0000"
    },
    "done": true
  },
  "stoneworks:recipes/building_blocks/mossy_andesite_brick_stairs_from_andesite_stonecutting": {
    "criteria": {
      "has_andesite": "2024-08-28 02:14:40 +0000"
    },
    "done": true
  },
  "minecraft:recipes/building_blocks/polished_andesite_from_andesite_stonecutting": {
    "criteria": {
      "has_andesite": "2024-08-28 02:14:40 +0000"
    },
    "done": true
  },
  "stoneworks:recipes/building_blocks/andesite_tile_stairs_from_andesite_stonecutting": {
    "criteria": {
      "has_andesite": "2024-08-28 02:14:40 +0000"
    },
    "done": true
  },
  "stoneworks:recipes/building_blocks/chiseled_andesite_from_andesite_stonecutting": {
    "criteria": {
      "has_andesite": "2024-08-28 02:14:40 +0000"
    },
    "done": true
  },
  "create:recipes/building_blocks/cut_andesite_wall_from_stone_types_andesite_stonecutting": {
    "criteria": {
      "has_stone_types_andesite": "2024-08-28 02:14:40 +0000"
    },
    "done": true
  },
  "create:recipes/building_blocks/small_andesite_brick_wall_from_stone_types_andesite_stonecutting": {
    "criteria": {
      "has_stone_types_andesite": "2024-08-28 02:14:40 +0000"
    },
    "done": true
  },
  "create:recipes/building_blocks/cut_andesite_brick_slab_from_stone_types_andesite_stonecutting": {
    "criteria": {
      "has_stone_types_andesite": "2024-08-28 02:14:40 +0000"
    },
    "done": true
  },
  "stoneworks:recipes/building_blocks/andesite_tile_wall_from_andesite_stonecutting": {
    "criteria": {
      "has_andesite": "2024-08-28 02:14:40 +0000"
    },
    "done": true
  },
  "stoneworks:recipes/building_blocks/andesite_shingles_from_andesite_stonecutting": {
    "criteria": {
      "has_andesite": "2024-08-28 02:14:40 +0000"
    },
    "done": true
  },
  "minecraft:recipes/decorations/andesite_wall_from_andesite_stonecutting": {
    "criteria": {
      "has_andesite": "2024-08-28 02:14:40 +0000"
    },
    "done": true
  },
  "create:recipes/building_blocks/cut_andesite_from_stone_types_andesite_stonecutting": {
    "criteria": {
      "has_stone_types_andesite": "2024-08-28 02:14:40 +0000"
    },
    "done": true
  },
  "stoneworks:recipes/building_blocks/andesite_brick_slab_from_andesite_stonecutting": {
    "criteria": {
      "has_andesite": "2024-08-28 02:14:40 +0000"
    },
    "done": true
  },
  "create:recipes/building_blocks/polished_cut_andesite_slab_from_stone_types_andesite_stonecutting": {
    "criteria": {
      "has_stone_types_andesite": "2024-08-28 02:14:40 +0000"
    },
    "done": true
  },
  "minecraft:recipes/building_blocks/andesite_stairs_from_andesite_stonecutting": {
    "criteria": {
      "has_andesite": "2024-08-28 02:14:40 +0000"
    },
    "done": true
  },
  "minecraft:recipes/building_blocks/polished_andesite": {
    "criteria": {
      "has_andesite": "2024-08-28 02:14:40 +0000"
    },
    "done": true
  },
  "stoneworks:recipes/building_blocks/mossy_cobbled_andesite_wall_from_andesite_stonecutting": {
    "criteria": {
      "has_andesite": "2024-08-28 02:14:40 +0000"
    },
    "done": true
  },
  "farmersdelight:main/get_fd_seed": {
    "criteria": {
      "tomato_seeds": "2024-08-28 02:18:06 +0000"
    },
    "done": true
  },
  "minecraft:recipes/food/cooked_chicken_from_campfire_cooking": {
    "criteria": {
      "has_chicken": "2024-08-28 02:19:10 +0000"
    },
    "done": true
  },
  "farmersdelight:recipes/cooking/chicken_soup": {
    "criteria": {
      "has_any_ingredient": "2024-08-28 02:19:10 +0000"
    },
    "done": true
  },
  "minecraft:recipes/food/cooked_chicken_from_smoking": {
    "criteria": {
      "has_chicken": "2024-08-28 02:19:10 +0000"
    },
    "done": true
  },
  "minecraft:recipes/food/cooked_chicken": {
    "criteria": {
      "has_chicken": "2024-08-28 02:19:10 +0000"
    },
    "done": true
  },
  "minecraft:recipes/combat/arrow": {
    "criteria": {
      "has_feather": "2024-08-28 02:19:12 +0000"
    },
    "done": true
  },
  "minecraft:recipes/misc/copper_ingot_from_blasting_raw_copper": {
    "criteria": {
      "has_raw_copper": "2024-08-28 02:20:41 +0000"
    },
    "done": true
  },
  "minecraft:recipes/building_blocks/raw_copper_block": {
    "criteria": {
      "has_raw_copper": "2024-08-28 02:20:41 +0000"
    },
    "done": true
  },
  "spelunkery:recipes/raw_copper": {
    "criteria": {
      "has_item": "2024-08-28 02:20:41 +0000"
    },
    "done": true
  },
  "minecraft:recipes/misc/copper_ingot_from_smelting_raw_copper": {
    "criteria": {
      "has_raw_copper": "2024-08-28 02:20:41 +0000"
    },
    "done": true
  },
  "minecraft:recipes/building_blocks/raw_iron_block": {
    "criteria": {
      "has_raw_iron": "2024-08-28 02:20:52 +0000"
    },
    "done": true
  },
  "minecraft:recipes/misc/iron_ingot_from_blasting_raw_iron": {
    "criteria": {
      "has_raw_iron": "2024-08-28 02:20:52 +0000"
    },
    "done": true
  },
  "minecraft:recipes/misc/iron_ingot_from_smelting_raw_iron": {
    "criteria": {
      "has_raw_iron": "2024-08-28 02:20:52 +0000"
    },
    "done": true
  },
  "spelunkery:recipes/raw_iron": {
    "criteria": {
      "has_item": "2024-08-28 02:20:52 +0000"
    },
    "done": true
  },
  "minecraft:recipes/decorations/smoker": {
    "criteria": {
      "has_furnace": "2024-08-28 02:27:54 +0000"
    },
    "done": true
  },
  "farmersdelight:recipes/food/roast_chicken_block": {
    "criteria": {
      "has_cooked_chicken": "2024-08-28 02:28:34 +0000"
    },
    "done": true
  },
  "farmersdelight:recipes/food/chicken_sandwich": {
    "criteria": {
      "has_cooked_chicken": "2024-08-28 02:28:34 +0000"
    },
    "done": true
  },
  "minecraft:husbandry/balanced_diet": {
    "criteria": {
      "cooked_porkchop": "2024-08-28 03:24:41 +0000",
      "cooked_mutton": "2024-08-29 02:27:48 +0000",
      "cooked_beef": "2024-08-28 03:16:53 +0000",
      "apple": "2024-08-28 04:17:26 +0000",
      "bread": "2024-08-28 03:31:52 +0000",
      "melon_slice": "2024-08-28 02:43:03 +0000",
      "cooked_chicken": "2024-08-28 02:28:36 +0000"
    },
    "done": false
  },
  "minecraft:husbandry/root": {
    "criteria": {
      "consumed_item": "2024-08-28 02:28:36 +0000"
    },
    "done": true
  },
  "minecraft:recipes/misc/iron_nugget_from_smelting": {
    "criteria": {
      "has_iron_pickaxe": "2024-08-28 02:31:30 +0000"
    },
    "done": true
  },
  "minecraft:story/iron_tools": {
    "criteria": {
      "iron_pickaxe": "2024-08-28 02:31:30 +0000"
    },
    "done": true
  },
  "minecraft:recipes/misc/iron_nugget_from_blasting": {
    "criteria": {
      "has_iron_pickaxe": "2024-08-28 02:31:30 +0000"
    },
    "done": true
  },
  "farmersdelight:recipes/food/melon_popsicle": {
    "criteria": {
      "has_melon": "2024-08-28 02:39:29 +0000"
    },
    "done": true
  },
  "minecraft:recipes/building_blocks/melon": {
    "criteria": {
      "has_melon": "2024-08-28 02:39:29 +0000"
    },
    "done": true
  },
  "minecraft:recipes/brewing/glistering_melon_slice": {
    "criteria": {
      "has_melon": "2024-08-28 02:39:29 +0000"
    },
    "done": true
  },
  "farmersdelight:recipes/food/melon_juice": {
    "criteria": {
      "has_melon_slice": "2024-08-28 02:39:29 +0000"
    },
    "done": true
  },
  "minecraft:recipes/misc/melon_seeds": {
    "criteria": {
      "has_melon": "2024-08-28 02:39:29 +0000"
    },
    "done": true
  },
  "minecraft:recipes/combat/leather_helmet": {
    "criteria": {
      "has_leather": "2024-08-28 02:41:43 +0000"
    },
    "done": true
  },
  "minecraft:recipes/combat/leather_chestplate": {
    "criteria": {
      "has_leather": "2024-08-28 02:41:43 +0000"
    },
    "done": true
  },
  "minecraft:recipes/misc/leather_horse_armor": {
    "criteria": {
      "has_leather": "2024-08-28 02:41:43 +0000"
    },
    "done": true
  },
  "farmersdelight:recipes/cooking/pasta_with_meatballs": {
    "criteria": {
      "has_any_ingredient": "2024-08-28 02:41:43 +0000"
    },
    "done": true
  },
  "minecraft:recipes/combat/leather_boots": {
    "criteria": {
      "has_leather": "2024-08-28 02:41:43 +0000"
    },
    "done": true
  },
  "minecraft:recipes/food/cooked_beef_from_smoking": {
    "criteria": {
      "has_beef": "2024-08-28 02:41:43 +0000"
    },
    "done": true
  },
  "minecraft:recipes/decorations/item_frame": {
    "criteria": {
      "has_leather": "2024-08-28 02:41:43 +0000"
    },
    "done": true
  },
  "minecraft:recipes/food/cooked_beef": {
    "criteria": {
      "has_beef": "2024-08-28 02:41:43 +0000"
    },
    "done": true
  },
  "minecraft:recipes/combat/leather_leggings": {
    "criteria": {
      "has_leather": "2024-08-28 02:41:43 +0000"
    },
    "done": true
  },
  "minecraft:recipes/food/cooked_beef_from_campfire_cooking": {
    "criteria": {
      "has_beef": "2024-08-28 02:41:43 +0000"
    },
    "done": true
  },
  "minecraft:recipes/decorations/grindstone": {
    "criteria": {
      "has_stone_slab": "2024-08-28 02:42:34 +0000"
    },
    "done": true
  },
  "create:recipes/building_blocks/crafting/kinetics/blue_seat": {
    "criteria": {
      "has_wool": "2024-08-28 02:42:58 +0000"
    },
    "done": true
  },
  "create:recipes/building_blocks/crafting/kinetics/light_blue_seat": {
    "criteria": {
      "has_wool": "2024-08-28 02:42:58 +0000"
    },
    "done": true
  },
  "create:recipes/building_blocks/crafting/kinetics/red_seat": {
    "criteria": {
      "has_wool": "2024-08-28 02:42:58 +0000"
    },
    "done": true
  },
  "create:recipes/building_blocks/crafting/kinetics/light_gray_seat": {
    "criteria": {
      "has_wool": "2024-08-28 02:42:58 +0000"
    },
    "done": true
  },
  "create:recipes/building_blocks/crafting/kinetics/cyan_seat": {
    "criteria": {
      "has_wool": "2024-08-28 02:42:58 +0000"
    },
    "done": true
  },
  "create:recipes/building_blocks/crafting/kinetics/pink_seat": {
    "criteria": {
      "has_wool": "2024-08-28 02:42:58 +0000"
    },
    "done": true
  },
  "minecraft:recipes/food/cooked_mutton_from_campfire_cooking": {
    "criteria": {
      "has_mutton": "2024-08-28 02:42:58 +0000"
    },
    "done": true
  },
  "farmersdelight:recipes/cooking/pasta_with_mutton_chop": {
    "criteria": {
      "has_any_ingredient": "2024-08-28 02:42:58 +0000"
    },
    "done": true
  },
  "minecraft:recipes/food/cooked_mutton_from_smoking": {
    "criteria": {
      "has_mutton": "2024-08-28 02:42:58 +0000"
    },
    "done": true
  },
  "create:recipes/building_blocks/crafting/kinetics/magenta_seat": {
    "criteria": {
      "has_wool": "2024-08-28 02:42:58 +0000"
    },
    "done": true
  },
  "create:recipes/building_blocks/crafting/kinetics/green_seat": {
    "criteria": {
      "has_wool": "2024-08-28 02:42:58 +0000"
    },
    "done": true
  },
  "create:recipes/building_blocks/crafting/kinetics/purple_seat": {
    "criteria": {
      "has_wool": "2024-08-28 02:42:58 +0000"
    },
    "done": true
  },
  "minecraft:recipes/decorations/white_bed": {
    "criteria": {
      "has_white_wool": "2024-08-28 02:42:58 +0000"
    },
    "done": true
  },
  "create:recipes/building_blocks/crafting/kinetics/brown_seat": {
    "criteria": {
      "has_wool": "2024-08-28 02:42:58 +0000"
    },
    "done": true
  },
  "create:recipes/building_blocks/crafting/kinetics/gray_seat": {
    "criteria": {
      "has_wool": "2024-08-28 02:42:58 +0000"
    },
    "done": true
  },
  "minecraft:recipes/decorations/painting": {
    "criteria": {
      "has_wool": "2024-08-28 02:42:58 +0000"
    },
    "done": true
  },
  "create:recipes/building_blocks/crafting/kinetics/orange_seat": {
    "criteria": {
      "has_wool": "2024-08-28 02:42:58 +0000"
    },
    "done": true
  },
  "minecolonies:recipes/misc/blockconstructiontape": {
    "criteria": {
      "has_wool": "2024-08-28 02:42:58 +0000"
    },
    "done": true
  },
  "minecraft:recipes/decorations/white_carpet": {
    "criteria": {
      "has_white_wool": "2024-08-28 02:42:58 +0000"
    },
    "done": true
  },
  "create:recipes/building_blocks/crafting/kinetics/black_seat": {
    "criteria": {
      "has_wool": "2024-08-28 02:42:58 +0000"
    },
    "done": true
  },
  "minecraft:recipes/food/cooked_mutton": {
    "criteria": {
      "has_mutton": "2024-08-28 02:42:58 +0000"
    },
    "done": true
  },
  "minecraft:recipes/decorations/white_banner": {
    "criteria": {
      "has_white_wool": "2024-08-28 02:42:58 +0000"
    },
    "done": true
  },
  "create:recipes/building_blocks/crafting/kinetics/white_seat": {
    "criteria": {
      "has_wool": "2024-08-28 02:42:58 +0000"
    },
    "done": true
  },
  "create:recipes/building_blocks/crafting/kinetics/lime_seat": {
    "criteria": {
      "has_wool": "2024-08-28 02:42:58 +0000"
    },
    "done": true
  },
  "createbigcannons:recipes/misc/gas_mask": {
    "criteria": {
      "has_wool": "2024-08-28 02:42:58 +0000"
    },
    "done": true
  },
  "create:recipes/building_blocks/crafting/kinetics/yellow_seat": {
    "criteria": {
      "has_wool": "2024-08-28 02:42:58 +0000"
    },
    "done": true
  },
  "minecraft:recipes/food/cooked_porkchop": {
    "criteria": {
      "has_porkchop": "2024-08-28 02:51:01 +0000"
    },
    "done": true
  },
  "minecraft:recipes/food/cooked_porkchop_from_smoking": {
    "criteria": {
      "has_porkchop": "2024-08-28 02:51:01 +0000"
    },
    "done": true
  },
  "farmersdelight:recipes/cooking/noodle_soup": {
    "criteria": {
      "has_any_ingredient": "2024-08-28 02:51:01 +0000"
    },
    "done": true
  },
  "minecraft:recipes/food/cooked_porkchop_from_campfire_cooking": {
    "criteria": {
      "has_porkchop": "2024-08-28 02:51:01 +0000"
    },
    "done": true
  },
  "farmersdelight:recipes/cooking/pumpkin_soup": {
    "criteria": {
      "has_any_ingredient": "2024-08-28 02:51:01 +0000"
    },
    "done": true
  },
  "createdeco:recipes/decorations/iron_catwalk_stairs_from_stonecutting": {
    "criteria": {
      "has_item": "2024-08-28 02:51:32 +0000"
    },
    "done": true
  },
  "minecraft:recipes/combat/iron_helmet": {
    "criteria": {
      "has_iron_ingot": "2024-08-28 02:51:32 +0000"
    },
    "done": true
  },
  "createdeco:recipes/decorations/iron_catwalk_from_stonecutting": {
    "criteria": {
      "has_item": "2024-08-28 02:51:32 +0000"
    },
    "done": true
  },
  "create:recipes/misc/crafting/materials/andesite_alloy": {
    "criteria": {
      "has_item": "2024-08-28 02:51:32 +0000"
    },
    "done": true
  },
  "immersive_weathering:recipes/iron_ingot": {
    "criteria": {
      "has_copper_block": "2024-08-28 02:51:32 +0000"
    },
    "done": true
  },
  "minecolonies:recipes/misc/chainmailleggings": {
    "criteria": {
      "has_iron": "2024-08-28 02:51:32 +0000"
    },
    "done": true
  },
  "minecraft:recipes/redstone/hopper": {
    "criteria": {
      "has_iron_ingot": "2024-08-28 02:51:32 +0000"
    },
    "done": true
  },
  "createdeco:recipes/building_blocks/iron_window": {
    "criteria": {
      "has_item": "2024-08-28 02:51:32 +0000"
    },
    "done": true
  },
  "minecraft:recipes/combat/iron_boots": {
    "criteria": {
      "has_iron_ingot": "2024-08-28 02:51:32 +0000"
    },
    "done": true
  },
  "minecraft:recipes/redstone/iron_trapdoor": {
    "criteria": {
      "has_iron_ingot": "2024-08-28 02:51:32 +0000"
    },
    "done": true
  },
  "farmersdelight:recipes/combat/iron_knife": {
    "criteria": {
      "has_iron_ingot": "2024-08-28 02:51:32 +0000"
    },
    "done": true
  },
  "minecraft:recipes/combat/iron_chestplate": {
    "criteria": {
      "has_iron_ingot": "2024-08-28 02:51:32 +0000"
    },
    "done": true
  },
  "minecraft:recipes/misc/iron_nugget": {
    "criteria": {
      "has_iron_ingot": "2024-08-28 02:51:32 +0000"
    },
    "done": true
  },
  "minecraft:recipes/misc/bucket": {
    "criteria": {
      "has_iron_ingot": "2024-08-28 02:51:32 +0000"
    },
    "done": true
  },
  "minecraft:story/smelt_iron": {
    "criteria": {
      "iron": "2024-08-28 02:51:32 +0000"
    },
    "done": true
  },
  "createdeco:recipes/decorations/iron_bars_overlay_from_stonecutting": {
    "criteria": {
      "has_item": "2024-08-28 02:51:32 +0000"
    },
    "done": true
  },
  "minecolonies:recipes/misc/chainmailchestplate": {
    "criteria": {
      "has_iron": "2024-08-28 02:51:32 +0000"
    },
    "done": true
  },
  "create:recipes/misc/crafting/kinetics/empty_blaze_burner": {
    "criteria": {
      "has_item": "2024-08-28 02:51:32 +0000"
    },
    "done": true
  },
  "minecraft:recipes/combat/iron_sword": {
    "criteria": {
      "has_iron_ingot": "2024-08-28 02:51:32 +0000"
    },
    "done": true
  },
  "minecraft:recipes/tools/iron_pickaxe": {
    "criteria": {
      "has_iron_ingot": "2024-08-28 02:51:32 +0000"
    },
    "done": true
  },
  "minecraft:recipes/combat/shield": {
    "criteria": {
      "has_iron_ingot": "2024-08-28 02:51:32 +0000"
    },
    "done": true
  },
  "minecolonies:recipes/misc/chainmailboots": {
    "criteria": {
      "has_iron": "2024-08-28 02:51:32 +0000"
    },
    "done": true
  },
  "minecraft:recipes/decorations/iron_bars": {
    "criteria": {
      "has_iron_ingot": "2024-08-28 02:51:32 +0000"
    },
    "done": true
  },
  "minecraft:recipes/tools/iron_axe": {
    "criteria": {
      "has_iron_ingot": "2024-08-28 02:51:32 +0000"
    },
    "done": true
  },
  "create:recipes/building_blocks/industrial_iron_block_from_ingots_iron_stonecutting": {
    "criteria": {
      "has_ingots_iron": "2024-08-28 02:51:32 +0000"
    },
    "done": true
  },
  "minecraft:recipes/redstone/iron_door": {
    "criteria": {
      "has_iron_ingot": "2024-08-28 02:51:32 +0000"
    },
    "done": true
  },
  "ae2:recipes/misc/decorative/light_detector": {
    "criteria": {
      "has_iron_ingot": "2024-08-28 02:51:32 +0000"
    },
    "done": true
  },
  "minecraft:recipes/tools/shears": {
    "criteria": {
      "has_iron_ingot": "2024-08-28 02:51:32 +0000"
    },
    "done": true
  },
  "minecraft:recipes/building_blocks/iron_block": {
    "criteria": {
      "has_iron_ingot": "2024-08-28 02:51:32 +0000"
    },
    "done": true
  },
  "farmersdelight:recipes/decorations/cooking_pot": {
    "criteria": {
      "has_iron_ingot": "2024-08-28 02:51:32 +0000"
    },
    "done": true
  },
  "createdeco:recipes/decorations/iron_mesh_fence_from_stonecutting": {
    "criteria": {
      "has_item": "2024-08-28 02:51:32 +0000"
    },
    "done": true
  },
  "createdeco:recipes/decorations/iron_ladder_from_stonecutting": {
    "criteria": {
      "has_item": "2024-08-28 02:51:32 +0000"
    },
    "done": true
  },
  "minecraft:recipes/tools/iron_shovel": {
    "criteria": {
      "has_iron_ingot": "2024-08-28 02:51:32 +0000"
    },
    "done": true
  },
  "minecolonies:recipes/misc/chainmailhelmet": {
    "criteria": {
      "has_iron": "2024-08-28 02:51:32 +0000"
    },
    "done": true
  },
  "createdeco:recipes/decorations/iron_catwalk_railing_from_stonecutting": {
    "criteria": {
      "has_item": "2024-08-28 02:51:32 +0000"
    },
    "done": true
  },
  "minecraft:recipes/combat/crossbow": {
    "criteria": {
      "has_iron_ingot": "2024-08-28 02:51:32 +0000"
    },
    "done": true
  },
  "createbigcannons:recipes/misc/solid_shot": {
    "criteria": {
      "has_iron_ingot": "2024-08-28 02:51:32 +0000"
    },
    "done": true
  },
  "minecraft:recipes/redstone/heavy_weighted_pressure_plate": {
    "criteria": {
      "has_iron_ingot": "2024-08-28 02:51:32 +0000"
    },
    "done": true
  },
  "minecraft:recipes/combat/iron_leggings": {
    "criteria": {
      "has_iron_ingot": "2024-08-28 02:51:32 +0000"
    },
    "done": true
  },
  "minecraft:recipes/transportation/minecart": {
    "criteria": {
      "has_iron_ingot": "2024-08-28 02:51:32 +0000"
    },
    "done": true
  },
  "minecraft:recipes/tools/iron_hoe": {
    "criteria": {
      "has_iron_ingot": "2024-08-28 02:51:32 +0000"
    },
    "done": true
  },
  "createdeco:recipes/decorations/iron_support_wedge_from_stonecutting": {
    "criteria": {
      "has_item": "2024-08-28 02:51:32 +0000"
    },
    "done": true
  },
  "minecraft:recipes/decorations/smithing_table": {
    "criteria": {
      "has_iron_ingot": "2024-08-28 02:51:32 +0000"
    },
    "done": true
  },
  "createdeco:recipes/decorations/iron_support": {
    "criteria": {
      "has_item": "2024-08-28 02:51:32 +0000"
    },
    "done": true
  },
  "sliceanddice:recipes/misc/slicer": {
    "criteria": {
      "has_tool": "2024-08-28 02:51:42 +0000"
    },
    "done": true
  },
  "minecraft:story/obtain_armor": {
    "criteria": {
      "iron_chestplate": "2024-08-28 02:52:17 +0000"
    },
    "done": true
  },
  "creategoggles:recipes/iron_backtank": {
    "criteria": {
      "has_backtank": "2024-08-28 02:52:17 +0000"
    },
    "done": true
  },
  "creategoggles:recipes/goggle_iron_helmet": {
    "criteria": {
      "has_helmet": "2024-08-28 02:53:42 +0000"
    },
    "done": true
  },
  "farmersdelight:recipes/food/roasted_mutton_chops": {
    "criteria": {
      "has_mutton": "2024-08-28 02:57:32 +0000"
    },
    "done": true
  },
  "farmersdelight:recipes/food/mutton_wrap": {
    "criteria": {
      "has_mutton": "2024-08-28 02:57:32 +0000"
    },
    "done": true
  },
  "farmersdelight:recipes/food/shepherds_pie_block": {
    "criteria": {
      "has_cooked_mutton": "2024-08-28 02:57:32 +0000"
    },
    "done": true
  },
  "minecraft:adventure/sleep_in_bed": {
    "criteria": {
      "slept_in_bed": "2024-08-28 02:57:48 +0000"
    },
    "done": true
  },
  "spelunkery:recipes/rough_emerald": {
    "criteria": {
      "has_item": "2024-08-28 02:58:13 +0000"
    },
    "done": true
  },
  "spelunkery:spelunkery/rough_gem": {
    "criteria": {
      "item": "2024-08-28 02:58:13 +0000"
    },
    "done": true
  },
  "immersive_weathering:immersive_weathering/dirts": {
    "criteria": {
      "sandy_dirt": "2024-08-28 03:01:48 +0000",
      "dirt": "2024-08-29 02:20:52 +0000"
    },
    "done": false
  },
  "minecraft:recipes/building_blocks/pink_terracotta": {
    "criteria": {
      "has_terracotta": "2024-08-28 03:01:53 +0000"
    },
    "done": true
  },
  "minecraft:recipes/building_blocks/blue_terracotta": {
    "criteria": {
      "has_terracotta": "2024-08-28 03:01:53 +0000"
    },
    "done": true
  },
  "minecraft:recipes/building_blocks/orange_terracotta": {
    "criteria": {
      "has_terracotta": "2024-08-28 03:01:53 +0000"
    },
    "done": true
  },
  "minecraft:recipes/building_blocks/magenta_terracotta": {
    "criteria": {
      "has_terracotta": "2024-08-28 03:01:53 +0000"
    },
    "done": true
  },
  "minecraft:recipes/building_blocks/cyan_terracotta": {
    "criteria": {
      "has_terracotta": "2024-08-28 03:01:53 +0000"
    },
    "done": true
  },
  "minecraft:recipes/building_blocks/lime_terracotta": {
    "criteria": {
      "has_terracotta": "2024-08-28 03:01:53 +0000"
    },
    "done": true
  },
  "minecraft:recipes/building_blocks/light_gray_terracotta": {
    "criteria": {
      "has_terracotta": "2024-08-28 03:01:53 +0000"
    },
    "done": true
  },
  "minecraft:recipes/building_blocks/red_terracotta": {
    "criteria": {
      "has_terracotta": "2024-08-28 03:01:53 +0000"
    },
    "done": true
  },
  "minecraft:recipes/building_blocks/white_terracotta": {
    "criteria": {
      "has_terracotta": "2024-08-28 03:01:53 +0000"
    },
    "done": true
  },
  "minecraft:recipes/building_blocks/gray_terracotta": {
    "criteria": {
      "has_terracotta": "2024-08-28 03:01:53 +0000"
    },
    "done": true
  },
  "minecraft:recipes/building_blocks/green_terracotta": {
    "criteria": {
      "has_terracotta": "2024-08-28 03:01:53 +0000"
    },
    "done": true
  },
  "minecraft:recipes/building_blocks/black_terracotta": {
    "criteria": {
      "has_terracotta": "2024-08-28 03:01:53 +0000"
    },
    "done": true
  },
  "minecraft:recipes/building_blocks/light_blue_terracotta": {
    "criteria": {
      "has_terracotta": "2024-08-28 03:01:53 +0000"
    },
    "done": true
  },
  "minecraft:recipes/building_blocks/yellow_terracotta": {
    "criteria": {
      "has_terracotta": "2024-08-28 03:01:53 +0000"
    },
    "done": true
  },
  "domum_ornamentum:recipes/tools/brown_bricks": {
    "criteria": {
      "has_item2_domum_ornamentum_brown_bricks": "2024-08-28 03:01:53 +0000",
      "has_item1_domum_ornamentum_brown_bricks": "2024-08-28 03:01:53 +0000"
    },
    "done": true
  },
  "minecraft:recipes/building_blocks/brown_terracotta": {
    "criteria": {
      "has_terracotta": "2024-08-28 03:01:53 +0000"
    },
    "done": true
  },
  "minecraft:recipes/building_blocks/purple_terracotta": {
    "criteria": {
      "has_terracotta": "2024-08-28 03:01:53 +0000"
    },
    "done": true
  },
  "domum_ornamentum:recipes/tools/brown_stone_bricks": {
    "criteria": {
      "has_item1_domum_ornamentum_brown_stone_bricks": "2024-08-28 03:01:53 +0000",
      "has_item2_domum_ornamentum_brown_stone_bricks": "2024-08-28 03:01:53 +0000"
    },
    "done": true
  },
  "stoneworks:recipes/building_blocks/granite_plates_from_granite_stonecutting": {
    "criteria": {
      "has_granite": "2024-08-28 03:06:43 +0000"
    },
    "done": true
  },
  "stoneworks:recipes/building_blocks/cobbled_granite_wall_from_granite_stonecutting": {
    "criteria": {
      "has_granite": "2024-08-28 03:06:43 +0000"
    },
    "done": true
  },
  "create:recipes/building_blocks/granite_from_stone_types_granite_stonecutting": {
    "criteria": {
      "has_stone_types_granite": "2024-08-28 03:06:43 +0000"
    },
    "done": true
  },
  "create:recipes/building_blocks/cut_granite_brick_slab_from_stone_types_granite_stonecutting": {
    "criteria": {
      "has_stone_types_granite": "2024-08-28 03:06:43 +0000"
    },
    "done": true
  },
  "stoneworks:recipes/building_blocks/cobbled_granite_slab_from_granite_stonecutting": {
    "criteria": {
      "has_granite": "2024-08-28 03:06:43 +0000"
    },
    "done": true
  },
  "stoneworks:recipes/building_blocks/mossy_granite_brick_stairs_from_granite_stonecutting": {
    "criteria": {
      "has_granite": "2024-08-28 03:06:43 +0000"
    },
    "done": true
  },
  "minecraft:recipes/building_blocks/granite_slab_from_granite_stonecutting": {
    "criteria": {
      "has_granite": "2024-08-28 03:06:43 +0000"
    },
    "done": true
  },
  "stoneworks:recipes/building_blocks/mossy_cobbled_granite_stairs_from_granite_stonecutting": {
    "criteria": {
      "has_granite": "2024-08-28 03:06:43 +0000"
    },
    "done": true
  },
  "minecraft:recipes/decorations/granite_wall_from_granite_stonecutting": {
    "criteria": {
      "has_granite": "2024-08-28 03:06:43 +0000"
    },
    "done": true
  },
  "create:recipes/building_blocks/small_granite_brick_stairs_from_stone_types_granite_stonecutting": {
    "criteria": {
      "has_stone_types_granite": "2024-08-28 03:06:43 +0000"
    },
    "done": true
  },
  "minecraft:recipes/building_blocks/granite_slab": {
    "criteria": {
      "has_granite": "2024-08-28 03:06:43 +0000"
    },
    "done": true
  },
  "create:recipes/building_blocks/cut_granite_from_stone_types_granite_stonecutting": {
    "criteria": {
      "has_stone_types_granite": "2024-08-28 03:06:43 +0000"
    },
    "done": true
  },
  "stoneworks:recipes/building_blocks/granite_pavers_from_granite_stonecutting": {
    "criteria": {
      "has_granite": "2024-08-28 03:06:43 +0000"
    },
    "done": true
  },
  "create:recipes/building_blocks/cut_granite_brick_stairs_from_stone_types_granite_stonecutting": {
    "criteria": {
      "has_stone_types_granite": "2024-08-28 03:06:43 +0000"
    },
    "done": true
  },
  "create:recipes/building_blocks/polished_cut_granite_from_stone_types_granite_stonecutting": {
    "criteria": {
      "has_stone_types_granite": "2024-08-28 03:06:43 +0000"
    },
    "done": true
  },
  "stoneworks:recipes/building_blocks/granite_tile_stairs_from_granite_stonecutting": {
    "criteria": {
      "has_granite": "2024-08-28 03:06:43 +0000"
    },
    "done": true
  },
  "stoneworks:recipes/building_blocks/granite_tiles_from_granite_stonecutting": {
    "criteria": {
      "has_granite": "2024-08-28 03:06:43 +0000"
    },
    "done": true
  },
  "minecraft:recipes/building_blocks/polished_granite_stairs_from_granite_stonecutting": {
    "criteria": {
      "has_granite": "2024-08-28 03:06:43 +0000"
    },
    "done": true
  },
  "stoneworks:recipes/building_blocks/mossy_granite_bricks_from_granite_stonecutting": {
    "criteria": {
      "has_granite": "2024-08-28 03:06:43 +0000"
    },
    "done": true
  },
  "stoneworks:recipes/building_blocks/granite_tile_slab_from_granite_stonecutting": {
    "criteria": {
      "has_granite": "2024-08-28 03:06:43 +0000"
    },
    "done": true
  },
  "create:recipes/building_blocks/polished_cut_granite_slab_from_stone_types_granite_stonecutting": {
    "criteria": {
      "has_stone_types_granite": "2024-08-28 03:06:43 +0000"
    },
    "done": true
  },
  "create:recipes/building_blocks/cut_granite_wall_from_stone_types_granite_stonecutting": {
    "criteria": {
      "has_stone_types_granite": "2024-08-28 03:06:43 +0000"
    },
    "done": true
  },
  "stoneworks:recipes/building_blocks/granite_paver_slab_from_granite_stonecutting": {
    "criteria": {
      "has_granite": "2024-08-28 03:06:43 +0000"
    },
    "done": true
  },
  "create:recipes/building_blocks/small_granite_brick_slab_from_stone_types_granite_stonecutting": {
    "criteria": {
      "has_stone_types_granite": "2024-08-28 03:06:43 +0000"
    },
    "done": true
  },
  "stoneworks:recipes/building_blocks/cobbled_granite_stairs_from_granite_stonecutting": {
    "criteria": {
      "has_granite": "2024-08-28 03:06:43 +0000"
    },
    "done": true
  },
  "minecraft:recipes/building_blocks/polished_granite": {
    "criteria": {
      "has_granite": "2024-08-28 03:06:43 +0000"
    },
    "done": true
  },
  "stoneworks:recipes/building_blocks/granite_brick_stairs_from_granite_stonecutting": {
    "criteria": {
      "has_granite": "2024-08-28 03:06:43 +0000"
    },
    "done": true
  },
  "stoneworks:recipes/building_blocks/granite_shingle_stairs_from_granite_stonecutting": {
    "criteria": {
      "has_granite": "2024-08-28 03:06:43 +0000"
    },
    "done": true
  },
  "stoneworks:recipes/building_blocks/mossy_cobbled_granite_wall_from_granite_stonecutting": {
    "criteria": {
      "has_granite": "2024-08-28 03:06:43 +0000"
    },
    "done": true
  },
  "stoneworks:recipes/building_blocks/cobbled_granite_from_granite_stonecutting": {
    "criteria": {
      "has_granite": "2024-08-28 03:06:43 +0000"
    },
    "done": true
  },
  "create:recipes/building_blocks/cut_granite_slab_from_stone_types_granite_stonecutting": {
    "criteria": {
      "has_stone_types_granite": "2024-08-28 03:06:43 +0000"
    },
    "done": true
  },
  "stoneworks:recipes/building_blocks/cracked_granite_bricks_from_granite_stonecutting": {
    "criteria": {
      "has_granite": "2024-08-28 03:06:43 +0000"
    },
    "done": true
  },
  "stoneworks:recipes/building_blocks/cracked_granite_tiles_from_granite_stonecutting": {
    "criteria": {
      "has_granite": "2024-08-28 03:06:43 +0000"
    },
    "done": true
  },
  "stoneworks:recipes/building_blocks/granite_plate_wall_from_granite_stonecutting": {
    "criteria": {
      "has_granite": "2024-08-28 03:06:43 +0000"
    },
    "done": true
  },
  "minecraft:recipes/building_blocks/polished_granite_from_granite_stonecutting": {
    "criteria": {
      "has_granite": "2024-08-28 03:06:43 +0000"
    },
    "done": true
  },
  "stoneworks:recipes/building_blocks/granite_brick_slab_from_granite_stonecutting": {
    "criteria": {
      "has_granite": "2024-08-28 03:06:43 +0000"
    },
    "done": true
  },
  "stoneworks:recipes/building_blocks/mossy_cobbled_granite_from_granite_stonecutting": {
    "criteria": {
      "has_granite": "2024-08-28 03:06:43 +0000"
    },
    "done": true
  },
  "stoneworks:recipes/building_blocks/mossy_granite_brick_slab_from_granite_stonecutting": {
    "criteria": {
      "has_granite": "2024-08-28 03:06:43 +0000"
    },
    "done": true
  },
  "minecraft:recipes/building_blocks/granite_stairs": {
    "criteria": {
      "has_granite": "2024-08-28 03:06:43 +0000"
    },
    "done": true
  },
  "minecraft:recipes/building_blocks/granite_stairs_from_granite_stonecutting": {
    "criteria": {
      "has_granite": "2024-08-28 03:06:43 +0000"
    },
    "done": true
  },
  "stoneworks:recipes/building_blocks/granite_bricks_from_granite_stonecutting": {
    "criteria": {
      "has_granite": "2024-08-28 03:06:43 +0000"
    },
    "done": true
  },
  "minecraft:recipes/decorations/granite_wall": {
    "criteria": {
      "has_granite": "2024-08-28 03:06:43 +0000"
    },
    "done": true
  },
  "minecraft:recipes/building_blocks/polished_granite_slab_from_granite_stonecutting": {
    "criteria": {
      "has_granite": "2024-08-28 03:06:43 +0000"
    },
    "done": true
  },
  "stoneworks:recipes/building_blocks/granite_plate_slab_from_granite_stonecutting": {
    "criteria": {
      "has_granite": "2024-08-28 03:06:43 +0000"
    },
    "done": true
  },
  "create:recipes/building_blocks/granite_pillar_from_stone_types_granite_stonecutting": {
    "criteria": {
      "has_stone_types_granite": "2024-08-28 03:06:43 +0000"
    },
    "done": true
  },
  "create:recipes/building_blocks/polished_cut_granite_wall_from_stone_types_granite_stonecutting": {
    "criteria": {
      "has_stone_types_granite": "2024-08-28 03:06:43 +0000"
    },
    "done": true
  },
  "stoneworks:recipes/building_blocks/granite_shingle_slab_from_granite_stonecutting": {
    "criteria": {
      "has_granite": "2024-08-28 03:06:43 +0000"
    },
    "done": true
  },
  "stoneworks:recipes/building_blocks/mossy_granite_brick_wall_from_granite_stonecutting": {
    "criteria": {
      "has_granite": "2024-08-28 03:06:43 +0000"
    },
    "done": true
  },
  "stoneworks:recipes/building_blocks/granite_tile_wall_from_granite_stonecutting": {
    "criteria": {
      "has_granite": "2024-08-28 03:06:43 +0000"
    },
    "done": true
  },
  "stoneworks:recipes/building_blocks/granite_brick_wall_from_granite_stonecutting": {
    "criteria": {
      "has_granite": "2024-08-28 03:06:43 +0000"
    },
    "done": true
  },
  "stoneworks:recipes/building_blocks/mossy_cobbled_granite_slab_from_granite_stonecutting": {
    "criteria": {
      "has_granite": "2024-08-28 03:06:43 +0000"
    },
    "done": true
  },
  "create:recipes/building_blocks/cut_granite_brick_wall_from_stone_types_granite_stonecutting": {
    "criteria": {
      "has_stone_types_granite": "2024-08-28 03:06:43 +0000"
    },
    "done": true
  },
  "create:recipes/building_blocks/polished_cut_granite_stairs_from_stone_types_granite_stonecutting": {
    "criteria": {
      "has_stone_types_granite": "2024-08-28 03:06:43 +0000"
    },
    "done": true
  },
  "create:recipes/building_blocks/layered_granite_from_stone_types_granite_stonecutting": {
    "criteria": {
      "has_stone_types_granite": "2024-08-28 03:06:43 +0000"
    },
    "done": true
  },
  "stoneworks:recipes/building_blocks/granite_paver_wall_from_granite_stonecutting": {
    "criteria": {
      "has_granite": "2024-08-28 03:06:43 +0000"
    },
    "done": true
  },
  "create:recipes/building_blocks/small_granite_brick_wall_from_stone_types_granite_stonecutting": {
    "criteria": {
      "has_stone_types_granite": "2024-08-28 03:06:43 +0000"
    },
    "done": true
  },
  "stoneworks:recipes/building_blocks/granite_shingles_from_granite_stonecutting": {
    "criteria": {
      "has_granite": "2024-08-28 03:06:43 +0000"
    },
    "done": true
  },
  "create:recipes/building_blocks/cut_granite_bricks_from_stone_types_granite_stonecutting": {
    "criteria": {
      "has_stone_types_granite": "2024-08-28 03:06:43 +0000"
    },
    "done": true
  },
  "stoneworks:recipes/building_blocks/granite_shingle_wall_from_granite_stonecutting": {
    "criteria": {
      "has_granite": "2024-08-28 03:06:43 +0000"
    },
    "done": true
  },
  "stoneworks:recipes/building_blocks/granite_plate_stairs_from_granite_stonecutting": {
    "criteria": {
      "has_granite": "2024-08-28 03:06:43 +0000"
    },
    "done": true
  },
  "stoneworks:recipes/building_blocks/granite_paver_stairs_from_granite_stonecutting": {
    "criteria": {
      "has_granite": "2024-08-28 03:06:43 +0000"
    },
    "done": true
  },
  "create:recipes/building_blocks/cut_granite_stairs_from_stone_types_granite_stonecutting": {
    "criteria": {
      "has_stone_types_granite": "2024-08-28 03:06:43 +0000"
    },
    "done": true
  },
  "create:recipes/building_blocks/small_granite_bricks_from_stone_types_granite_stonecutting": {
    "criteria": {
      "has_stone_types_granite": "2024-08-28 03:06:43 +0000"
    },
    "done": true
  },
  "stoneworks:recipes/building_blocks/granite_pillar_from_granite_stonecutting": {
    "criteria": {
      "has_granite": "2024-08-28 03:06:43 +0000"
    },
    "done": true
  },
  "stoneworks:recipes/building_blocks/chiseled_granite_from_granite_stonecutting": {
    "criteria": {
      "has_granite": "2024-08-28 03:06:43 +0000"
    },
    "done": true
  },
  "ae2:recipes/misc/shaped/not_so_mysterious_cube": {
    "criteria": {
      "press": "2024-08-28 03:09:55 +0000"
    },
    "done": true
  },
  "ae2:main/presses": {
    "criteria": {
      "calculation": "2024-08-28 03:09:55 +0000",
      "silicon": "2024-08-28 03:09:56 +0000",
      "engineering": "2024-08-28 03:09:55 +0000",
      "logic": "2024-08-28 03:09:55 +0000"
    },
    "done": true
  },
  "minecraft:recipes/transportation/spruce_chest_boat": {
    "criteria": {
      "has_boat": "2024-08-28 03:10:27 +0000"
    },
    "done": true
  },
  "minecraft:recipes/transportation/mangrove_chest_boat": {
    "criteria": {
      "has_boat": "2024-08-28 03:10:27 +0000"
    },
    "done": true
  },
  "minecraft:recipes/transportation/oak_chest_boat": {
    "criteria": {
      "has_boat": "2024-08-28 03:10:27 +0000"
    },
    "done": true
  },
  "minecraft:recipes/transportation/dark_oak_chest_boat": {
    "criteria": {
      "has_boat": "2024-08-28 03:10:27 +0000"
    },
    "done": true
  },
  "minecraft:recipes/transportation/jungle_chest_boat": {
    "criteria": {
      "has_boat": "2024-08-28 03:10:27 +0000"
    },
    "done": true
  },
  "minecraft:recipes/transportation/bamboo_chest_raft": {
    "criteria": {
      "has_boat": "2024-08-28 03:10:27 +0000"
    },
    "done": true
  },
  "minecraft:recipes/transportation/acacia_chest_boat": {
    "criteria": {
      "has_boat": "2024-08-28 03:10:27 +0000"
    },
    "done": true
  },
  "minecolonies:recipes/misc/supplychestdeployer": {
    "criteria": {
      "has_boat": "2024-08-28 03:10:27 +0000"
    },
    "done": true
  },
  "minecraft:recipes/transportation/cherry_chest_boat": {
    "criteria": {
      "has_boat": "2024-08-28 03:10:27 +0000"
    },
    "done": true
  },
  "minecraft:recipes/transportation/birch_chest_boat": {
    "criteria": {
      "has_boat": "2024-08-28 03:10:27 +0000"
    },
    "done": true
  },
  "minecraft:recipes/misc/pink_dye_from_pink_tulip": {
    "criteria": {
      "has_pink_tulip": "2024-08-28 03:17:57 +0000"
    },
    "done": true
  },
  "minecraft:recipes/misc/blue_dye_from_cornflower": {
    "criteria": {
      "has_cornflower": "2024-08-28 03:18:00 +0000"
    },
    "done": true
  },
  "minecraft:recipes/redstone/target": {
    "criteria": {
      "has_hay_block": "2024-08-28 03:21:27 +0000"
    },
    "done": true
  },
  "createbigcannons:recipes/misc/smoke_shell": {
    "criteria": {
      "has_hay_block": "2024-08-28 03:21:27 +0000"
    },
    "done": true
  },
  "minecraft:recipes/misc/wheat": {
    "criteria": {
      "has_hay_block": "2024-08-28 03:21:27 +0000"
    },
    "done": true
  },
  "minecraft:recipes/misc/light_gray_dye_from_azure_bluet": {
    "criteria": {
      "has_azure_bluet": "2024-08-28 03:31:08 +0000"
    },
    "done": true
  },
  "minecraft:recipes/food/bread": {
    "criteria": {
      "has_the_recipe": "2024-08-28 03:31:36 +0000"
    },
    "done": true
  },
  "farmersdelight:recipes/food/pie_crust": {
    "criteria": {
      "has_wheat": "2024-08-28 03:31:45 +0000"
    },
    "done": true
  },
  "farmersdelight:recipes/food/wheat_dough_from_eggs": {
    "criteria": {
      "has_wheat": "2024-08-28 03:31:45 +0000"
    },
    "done": true
  },
  "minecraft:recipes/building_blocks/hay_block": {
    "criteria": {
      "has_wheat": "2024-08-28 03:31:45 +0000"
    },
    "done": true
  },
  "domum_ornamentum:recipes/tools/wheat_extra": {
    "criteria": {
      "has_material": "2024-08-28 03:31:45 +0000"
    },
    "done": true
  },
  "farmersdelight:recipes/food/wheat_dough_from_water": {
    "criteria": {
      "has_wheat": "2024-08-28 03:31:45 +0000"
    },
    "done": true
  },
  "farmersdelight:recipes/cooking/apple_cider": {
    "criteria": {
      "has_apple": "2024-08-28 03:32:30 +0000"
    },
    "done": true
  },
  "spelunkery:spelunkery/rough_diamond": {
    "criteria": {
      "item": "2024-08-28 03:34:28 +0000"
    },
    "done": true
  },
  "spelunkery:recipes/rough_diamond": {
    "criteria": {
      "has_item": "2024-08-28 03:34:28 +0000"
    },
    "done": true
  },
  "spelunkery:recipes/rough_diamond_shard": {
    "criteria": {
      "has_item": "2024-08-28 03:34:33 +0000"
    },
    "done": true
  },
  "create_central_kitchen:recipes/crafting/tomato_sauce_bucket_from_bowls": {
    "criteria": {
      "has_bucket": "2024-08-28 03:35:19 +0000"
    },
    "done": true
  },
  "minecraft:recipes/brewing/cauldron": {
    "criteria": {
      "has_water_bucket": "2024-08-28 03:36:00 +0000"
    },
    "done": true
  },
  "minecraft:recipes/redstone/slime_block": {
    "criteria": {
      "has_slime_ball": "2024-08-28 03:39:59 +0000"
    },
    "done": true
  },
  "minecraft:recipes/tools/lead": {
    "criteria": {
      "has_slime_ball": "2024-08-28 03:39:59 +0000"
    },
    "done": true
  },
  "minecraft:recipes/redstone/sticky_piston": {
    "criteria": {
      "has_slime_ball": "2024-08-28 03:39:59 +0000"
    },
    "done": true
  },
  "minecraft:recipes/building_blocks/polished_deepslate": {
    "criteria": {
      "has_cobbled_deepslate": "2024-08-28 03:42:58 +0000"
    },
    "done": true
  },
  "minecraft:recipes/building_blocks/polished_deepslate_from_cobbled_deepslate_stonecutting": {
    "criteria": {
      "has_cobbled_deepslate": "2024-08-28 03:42:58 +0000"
    },
    "done": true
  },
  "minecraft:recipes/decorations/cobbled_deepslate_wall": {
    "criteria": {
      "has_cobbled_deepslate": "2024-08-28 03:42:58 +0000"
    },
    "done": true
  },
  "minecraft:recipes/decorations/polished_deepslate_wall_from_cobbled_deepslate_stonecutting": {
    "criteria": {
      "has_cobbled_deepslate": "2024-08-28 03:42:58 +0000"
    },
    "done": true
  },
  "minecraft:recipes/building_blocks/polished_deepslate_slab_from_cobbled_deepslate_stonecutting": {
    "criteria": {
      "has_cobbled_deepslate": "2024-08-28 03:42:58 +0000"
    },
    "done": true
  },
  "minecraft:recipes/building_blocks/cobbled_deepslate_stairs": {
    "criteria": {
      "has_cobbled_deepslate": "2024-08-28 03:42:58 +0000"
    },
    "done": true
  },
  "minecraft:recipes/building_blocks/deepslate_bricks_from_cobbled_deepslate_stonecutting": {
    "criteria": {
      "has_cobbled_deepslate": "2024-08-28 03:42:58 +0000"
    },
    "done": true
  },
  "minecraft:recipes/building_blocks/deepslate_tile_stairs_from_cobbled_deepslate_stonecutting": {
    "criteria": {
      "has_cobbled_deepslate": "2024-08-28 03:42:58 +0000"
    },
    "done": true
  },
  "minecraft:recipes/building_blocks/cobbled_deepslate_slab": {
    "criteria": {
      "has_cobbled_deepslate": "2024-08-28 03:42:58 +0000"
    },
    "done": true
  },
  "minecraft:recipes/building_blocks/polished_deepslate_stairs_from_cobbled_deepslate_stonecutting": {
    "criteria": {
      "has_cobbled_deepslate": "2024-08-28 03:42:58 +0000"
    },
    "done": true
  },
  "minecraft:recipes/decorations/deepslate_brick_wall_from_cobbled_deepslate_stonecutting": {
    "criteria": {
      "has_cobbled_deepslate": "2024-08-28 03:42:58 +0000"
    },
    "done": true
  },
  "minecraft:recipes/building_blocks/cobbled_deepslate_slab_from_cobbled_deepslate_stonecutting": {
    "criteria": {
      "has_cobbled_deepslate": "2024-08-28 03:42:58 +0000"
    },
    "done": true
  },
  "minecraft:recipes/building_blocks/deepslate_tile_slab_from_cobbled_deepslate_stonecutting": {
    "criteria": {
      "has_cobbled_deepslate": "2024-08-28 03:42:58 +0000"
    },
    "done": true
  },
  "minecraft:recipes/decorations/deepslate_tile_wall_from_cobbled_deepslate_stonecutting": {
    "criteria": {
      "has_cobbled_deepslate": "2024-08-28 03:42:58 +0000"
    },
    "done": true
  },
  "minecraft:recipes/building_blocks/deepslate_brick_stairs_from_cobbled_deepslate_stonecutting": {
    "criteria": {
      "has_cobbled_deepslate": "2024-08-28 03:42:58 +0000"
    },
    "done": true
  },
  "minecraft:recipes/building_blocks/chiseled_deepslate_from_cobbled_deepslate_stonecutting": {
    "criteria": {
      "has_cobbled_deepslate": "2024-08-28 03:42:58 +0000"
    },
    "done": true
  },
  "minecraft:recipes/decorations/cobbled_deepslate_wall_from_cobbled_deepslate_stonecutting": {
    "criteria": {
      "has_cobbled_deepslate": "2024-08-28 03:42:58 +0000"
    },
    "done": true
  },
  "minecraft:recipes/building_blocks/cobbled_deepslate_stairs_from_cobbled_deepslate_stonecutting": {
    "criteria": {
      "has_cobbled_deepslate": "2024-08-28 03:42:58 +0000"
    },
    "done": true
  },
  "minecraft:recipes/building_blocks/deepslate": {
    "criteria": {
      "has_cobbled_deepslate": "2024-08-28 03:42:58 +0000"
    },
    "done": true
  },
  "minecraft:recipes/building_blocks/deepslate_brick_slab_from_cobbled_deepslate_stonecutting": {
    "criteria": {
      "has_cobbled_deepslate": "2024-08-28 03:42:58 +0000"
    },
    "done": true
  },
  "minecraft:recipes/building_blocks/deepslate_tiles_from_cobbled_deepslate_stonecutting": {
    "criteria": {
      "has_cobbled_deepslate": "2024-08-28 03:42:58 +0000"
    },
    "done": true
  },
  "minecraft:recipes/misc/gold_ingot_from_blasting_raw_gold": {
    "criteria": {
      "has_raw_gold": "2024-08-28 03:45:53 +0000"
    },
    "done": true
  },
  "minecraft:recipes/misc/gold_ingot_from_smelting_raw_gold": {
    "criteria": {
      "has_raw_gold": "2024-08-28 03:45:53 +0000"
    },
    "done": true
  },
  "minecraft:recipes/building_blocks/raw_gold_block": {
    "criteria": {
      "has_raw_gold": "2024-08-28 03:45:53 +0000"
    },
    "done": true
  },
  "spelunkery:recipes/raw_gold": {
    "criteria": {
      "has_item": "2024-08-28 03:45:53 +0000"
    },
    "done": true
  },
  "spelunkery:recipes/raw_gold_nugget": {
    "criteria": {
      "has_item": "2024-08-28 03:46:08 +0000"
    },
    "done": true
  },
  "computercraft:recipes/redstone/printer": {
    "criteria": {
      "has_computer": "2024-08-28 04:03:05 +0000"
    },
    "done": true
  },
  "computercraft:recipes/redstone/wireless_modem_advanced": {
    "criteria": {
      "has_computer": "2024-08-28 04:03:05 +0000"
    },
    "done": true
  },
  "computercraft:recipes/redstone/speaker": {
    "criteria": {
      "has_computer": "2024-08-28 04:03:05 +0000"
    },
    "done": true
  },
  "computercraft:recipes/redstone/monitor_normal": {
    "criteria": {
      "has_computer": "2024-08-28 04:03:05 +0000"
    },
    "done": true
  },
  "computercraft:recipes/redstone/cable": {
    "criteria": {
      "has_computer": "2024-08-28 04:03:05 +0000"
    },
    "done": true
  },
  "computercraft:recipes/redstone/disk_drive": {
    "criteria": {
      "has_computer": "2024-08-28 04:03:05 +0000"
    },
    "done": true
  },
  "computercraft:recipes/redstone/wired_modem": {
    "criteria": {
      "has_computer": "2024-08-28 04:03:05 +0000"
    },
    "done": true
  },
  "computercraft:recipes/redstone/pocket_computer_normal": {
    "criteria": {
      "has_computer": "2024-08-28 04:03:05 +0000"
    },
    "done": true
  },
  "computercraft:recipes/redstone/wireless_modem_normal": {
    "criteria": {
      "has_computer": "2024-08-28 04:03:05 +0000"
    },
    "done": true
  },
  "computercraft:recipes/redstone/pocket_computer_advanced": {
    "criteria": {
      "has_computer": "2024-08-28 04:03:05 +0000"
    },
    "done": true
  },
  "computercraft:recipes/decorations/skull_dan200": {
    "criteria": {
      "has_computer": "2024-08-28 04:03:05 +0000"
    },
    "done": true
  },
  "computercraft:recipes/redstone/monitor_advanced": {
    "criteria": {
      "has_computer": "2024-08-28 04:03:05 +0000"
    },
    "done": true
  },
  "minecraft:recipes/misc/red_dye_from_poppy": {
    "criteria": {
      "has_poppy": "2024-08-28 04:15:32 +0000"
    },
    "done": true
  },
  "minecraft:story/deflect_arrow": {
    "criteria": {
      "deflected_projectile": "2024-08-29 01:32:17 +0000"
    },
    "done": true
  },
  "minecraft:adventure/shoot_arrow": {
    "criteria": {
      "shot_arrow": "2024-08-29 01:32:40 +0000"
    },
    "done": true
  },
  "travelersbackpack:recipes/misc/crafting_upgrade": {
    "criteria": {
      "has_crafting_table": "2024-08-29 01:19:58 +0000"
    },
    "done": true
  },
  "minecraft:recipes/building_blocks/stone_stairs_from_stone_stonecutting": {
    "criteria": {
      "has_stone": "2024-08-29 02:31:26 +0000"
    },
    "done": true
  },
  "stoneworks:recipes/building_blocks/stone_shingle_wall_from_stone_stonecutting": {
    "criteria": {
      "has_stone": "2024-08-29 02:31:26 +0000"
    },
    "done": true
  },
  "travelersbackpack:recipes/misc/iron": {
    "criteria": {
      "has_iron_ingot": "2024-08-29 01:19:58 +0000"
    },
    "done": true
  },
  "stoneworks:recipes/building_blocks/stone_tile_slab_from_stone_stonecutting": {
    "criteria": {
      "has_stone": "2024-08-29 02:31:26 +0000"
    },
    "done": true
  },
  "minecraft:recipes/building_blocks/chiseled_stone_bricks_from_stone_bricks_stonecutting": {
    "criteria": {
      "has_stone_bricks": "2024-08-29 02:32:06 +0000"
    },
    "done": true
  },
  "minecolonies:recipes/misc/questlog": {
    "criteria": {
      "has_build_tool": "2024-08-29 01:45:35 +0000"
    },
    "done": true
  },
  "minecolonies:minecolonies/fulfill_request": {
    "criteria": {
      "click_gui_button_fulfill": "2024-08-29 02:16:48 +0000"
    },
    "done": true
  },
  "minecolonies:recipes/misc/build_goggles": {
    "criteria": {
      "has_build_tool": "2024-08-29 01:45:35 +0000"
    },
    "done": true
  },
  "minecraft:recipes/building_blocks/stone_stairs": {
    "criteria": {
      "has_stone": "2024-08-29 02:31:26 +0000"
    },
    "done": true
  },
  "travelersbackpack:recipes/misc/coal": {
    "criteria": {
      "has_coal": "2024-08-29 01:19:58 +0000"
    },
    "done": true
  },
  "minecolonies:recipes/misc/blockhutstonesmeltery": {
    "criteria": {
      "has_items": "2024-08-29 02:32:06 +0000"
    },
    "done": true
  },
  "domum_ornamentum:recipes/tools/white_paper_extra": {
    "criteria": {
      "has_material": "2024-08-29 01:45:40 +0000"
    },
    "done": true
  },
  "minecolonies:recipes/misc/blockwaypoint": {
    "criteria": {
      "has_build_tool": "2024-08-29 01:45:35 +0000"
    },
    "done": true
  },
  "immersive_weathering:recipes/stone_bricks": {
    "criteria": {
      "has_copper_block": "2024-08-29 02:32:06 +0000"
    },
    "done": true
  },
  "stoneworks:recipes/building_blocks/stone_paver_wall_from_stone_stonecutting": {
    "criteria": {
      "has_stone": "2024-08-29 02:31:26 +0000"
    },
    "done": true
  },
  "create:recipes/misc/crafting/schematics/empty_schematic": {
    "criteria": {
      "has_item": "2024-08-29 01:45:40 +0000"
    },
    "done": true
  },
  "minecraft:recipes/misc/yellow_dye_from_dandelion": {
    "criteria": {
      "has_dandelion": "2024-08-29 02:33:58 +0000"
    },
    "done": true
  },
  "minecraft:recipes/decorations/stonecutter": {
    "criteria": {
      "has_stone": "2024-08-29 02:31:26 +0000"
    },
    "done": true
  },
  "minecolonies:recipes/misc/clipboard": {
    "criteria": {
      "has_build_tool": "2024-08-29 01:45:35 +0000"
    },
    "done": true
  },
  "stoneworks:recipes/building_blocks/stone_pillar_from_stone_stonecutting": {
    "criteria": {
      "has_stone": "2024-08-29 02:31:26 +0000"
    },
    "done": true
  },
  "minecraft:recipes/decorations/stone_brick_walls_from_stone_stonecutting": {
    "criteria": {
      "has_stone": "2024-08-29 02:31:26 +0000"
    },
    "done": true
  },
  "minecraft:recipes/building_blocks/stone_brick_slab_from_stone_stonecutting": {
    "criteria": {
      "has_stone": "2024-08-29 02:31:26 +0000"
    },
    "done": true
  },
  "minecraft:recipes/building_blocks/stone_brick_stairs_from_stone_stonecutting": {
    "criteria": {
      "has_stone": "2024-08-29 02:31:26 +0000"
    },
    "done": true
  },
  "domum_ornamentum:recipes/tools/paper_extra": {
    "criteria": {
      "has_material": "2024-08-29 01:45:40 +0000"
    },
    "done": true
  },
  "minecraft:recipes/building_blocks/stone_brick_slab_from_stone_bricks_stonecutting": {
    "criteria": {
      "has_stone_bricks": "2024-08-29 02:32:06 +0000"
    },
    "done": true
  },
  "minecraft:recipes/building_blocks/stone_slab_from_stone_stonecutting": {
    "criteria": {
      "has_stone": "2024-08-29 02:31:26 +0000"
    },
    "done": true
  },
  "stoneworks:recipes/building_blocks/stone_plate_slab_from_stone_stonecutting": {
    "criteria": {
      "has_stone": "2024-08-29 02:31:26 +0000"
    },
    "done": true
  },
  "stoneworks:recipes/building_blocks/stone_plate_stairs_from_stone_stonecutting": {
    "criteria": {
      "has_stone": "2024-08-29 02:31:26 +0000"
    },
    "done": true
  },
  "stoneworks:recipes/building_blocks/stone_plate_wall_from_stone_stonecutting": {
    "criteria": {
      "has_stone": "2024-08-29 02:31:26 +0000"
    },
    "done": true
  },
  "minecraft:recipes/building_blocks/stone_bricks": {
    "criteria": {
      "has_stone": "2024-08-29 02:31:26 +0000"
    },
    "done": true
  },
  "stoneworks:recipes/building_blocks/stone_pavers_from_stone_stonecutting": {
    "criteria": {
      "has_stone": "2024-08-29 02:31:26 +0000"
    },
    "done": true
  },
  "travelersbackpack:recipes/misc/backpack_tank": {
    "criteria": {
      "has_iron": "2024-08-29 01:19:58 +0000"
    },
    "done": true
  },
  "minecolonies:recipes/misc/blockhutstonemason": {
    "criteria": {
      "has_items": "2024-08-29 02:32:06 +0000"
    },
    "done": true
  },
  "minecraft:recipes/building_blocks/stone_brick_stairs": {
    "criteria": {
      "has_stone_bricks": "2024-08-29 02:32:06 +0000"
    },
    "done": true
  },
  "minecraft:recipes/building_blocks/stone_bricks_from_stone_stonecutting": {
    "criteria": {
      "has_stone": "2024-08-29 02:31:26 +0000"
    },
    "done": true
  },
  "minecraft:recipes/building_blocks/stone_slab": {
    "criteria": {
      "has_stone": "2024-08-29 02:31:26 +0000"
    },
    "done": true
  },
  "stoneworks:recipes/building_blocks/stone_tile_stairs_from_stone_stonecutting": {
    "criteria": {
      "has_stone": "2024-08-29 02:31:26 +0000"
    },
    "done": true
  },
  "minecraft:recipes/redstone/stone_button": {
    "criteria": {
      "has_stone": "2024-08-29 02:31:26 +0000"
    },
    "done": true
  },
  "stoneworks:recipes/building_blocks/stone_paver_stairs_from_stone_stonecutting": {
    "criteria": {
      "has_stone": "2024-08-29 02:31:26 +0000"
    },
    "done": true
  },
  "minecraft:recipes/redstone/stone_pressure_plate": {
    "criteria": {
      "has_stone": "2024-08-29 02:31:26 +0000"
    },
    "done": true
  },
  "minecolonies:recipes/misc/blockhutdeliverymaniron": {
    "criteria": {
      "has_items": "2024-08-29 01:45:35 +0000"
    },
    "done": true
  },
  "minecolonies:minecolonies/start_builder": {
    "criteria": {
      "builder_request": "2024-08-29 02:15:34 +0000"
    },
    "done": true
  },
  "minecraft:adventure/ol_betsy": {
    "criteria": {
      "shot_crossbow": "2024-08-29 01:32:40 +0000"
    },
    "done": true
  },
  "minecolonies:recipes/misc/blockhutblacksmith": {
    "criteria": {
      "has_items": "2024-08-29 01:45:35 +0000"
    },
    "done": true
  },
  "stoneworks:recipes/building_blocks/stone_tile_wall_from_stone_stonecutting": {
    "criteria": {
      "has_stone": "2024-08-29 02:31:26 +0000"
    },
    "done": true
  },
  "minecraft:recipes/building_blocks/stone_brick_slab": {
    "criteria": {
      "has_stone_bricks": "2024-08-29 02:32:06 +0000"
    },
    "done": true
  },
  "stoneworks:recipes/building_blocks/stone_paver_slab_from_stone_stonecutting": {
    "criteria": {
      "has_stone": "2024-08-29 02:31:26 +0000"
    },
    "done": true
  },
  "minecolonies:recipes/misc/blockhutcrusher": {
    "criteria": {
      "has_items": "2024-08-29 01:45:35 +0000"
    },
    "done": true
  },
  "minecolonies:recipes/misc/blockhutshepherd": {
    "criteria": {
      "has_items": "2024-08-29 02:16:29 +0000"
    },
    "done": true
  },
  "minecolonies:recipes/misc/blockhuttownhall": {
    "criteria": {
      "has_items": "2024-08-29 01:45:35 +0000"
    },
    "done": true
  },
  "minecolonies:recipes/misc/resourcescroll": {
    "criteria": {
      "has_build_tool": "2024-08-29 01:45:35 +0000"
    },
    "done": true
  },
  "minecolonies:recipes/misc/blockminecoloniesrack": {
    "criteria": {
      "has_build_tool": "2024-08-29 01:45:35 +0000"
    },
    "done": true
  },
  "minecolonies:minecolonies/check_out_guide": {
    "criteria": {
      "click_gui_button_close": "2024-08-29 02:15:05 +0000"
    },
    "done": true
  },
  "stoneworks:recipes/building_blocks/stone_plates_from_stone_stonecutting": {
    "criteria": {
      "has_stone": "2024-08-29 02:31:26 +0000"
    },
    "done": true
  },
  "minecraft:recipes/decorations/stone_brick_wall": {
    "criteria": {
      "has_stone_bricks": "2024-08-29 02:32:06 +0000"
    },
    "done": true
  },
  "stoneworks:recipes/building_blocks/stone_shingle_slab_from_stone_stonecutting": {
    "criteria": {
      "has_stone": "2024-08-29 02:31:26 +0000"
    },
    "done": true
  },
  "minecraft:recipes/misc/book": {
    "criteria": {
      "has_paper": "2024-08-29 01:45:40 +0000"
    },
    "done": true
  },
  "minecraft:recipes/building_blocks/cracked_stone_bricks": {
    "criteria": {
      "has_stone_bricks": "2024-08-29 02:32:06 +0000"
    },
    "done": true
  },
  "minecraft:recipes/building_blocks/stone_brick_stairs_from_stone_bricks_stonecutting": {
    "criteria": {
      "has_stone_bricks": "2024-08-29 02:32:06 +0000"
    },
    "done": true
  },
  "stoneworks:recipes/building_blocks/stone_shingles_from_stone_stonecutting": {
    "criteria": {
      "has_stone": "2024-08-29 02:31:26 +0000"
    },
    "done": true
  },
  "minecraft:recipes/building_blocks/chiseled_stone_bricks": {
    "criteria": {
      "has_tag": "2024-08-29 02:32:06 +0000"
    },
    "done": true
  },
  "create:recipes/misc/crafting/schematics/schematic_and_quill": {
    "criteria": {
      "has_item": "2024-08-29 01:45:40 +0000"
    },
    "done": true
  },
  "minecraft:recipes/building_blocks/smooth_stone": {
    "criteria": {
      "has_stone": "2024-08-29 02:31:26 +0000"
    },
    "done": true
  },
  "minecolonies:recipes/misc/blockhutsmeltery": {
    "criteria": {
      "has_items": "2024-08-29 01:45:35 +0000"
    },
    "done": true
  },
  "minecraft:recipes/decorations/stone_brick_wall_from_stone_bricks_stonecutting": {
    "criteria": {
      "has_stone_bricks": "2024-08-29 02:32:06 +0000"
    },
    "done": true
  },
  "create:recipes/misc/crafting/materials/sand_paper": {
    "criteria": {
      "has_item": "2024-08-29 01:45:40 +0000"
    },
    "done": true
  },
  "minecolonies:recipes/misc/barrel_block": {
    "criteria": {
      "has_items": "2024-08-29 01:45:35 +0000"
    },
    "done": true
  },
  "create:recipes/misc/crafting/materials/red_sand_paper": {
    "criteria": {
      "has_item": "2024-08-29 01:45:40 +0000"
    },
    "done": true
  },
  "travelersbackpack:recipes/misc/iron_tier_upgrade": {
    "criteria": {
      "has_iron_ingot": "2024-08-29 01:19:58 +0000"
    },
    "done": true
  },
  "travelersbackpack:recipes/misc/hose_nozzle": {
    "criteria": {
      "has_iron": "2024-08-29 01:19:58 +0000"
    },
    "done": true
  },
  "stoneworks:recipes/building_blocks/stone_shingle_stairs_from_stone_stonecutting": {
    "criteria": {
      "has_stone": "2024-08-29 02:31:26 +0000"
    },
    "done": true
  },
  "stoneworks:recipes/building_blocks/cracked_stone_tiles_from_stone_stonecutting": {
    "criteria": {
      "has_stone": "2024-08-29 02:31:26 +0000"
    },
    "done": true
  },
  "minecraft:recipes/building_blocks/chiseled_stone_bricks_stone_from_stonecutting": {
    "criteria": {
      "has_stone": "2024-08-29 02:31:26 +0000"
    },
    "done": true
  },
  "stoneworks:recipes/building_blocks/stone_tiles_from_stone_stonecutting": {
    "criteria": {
      "has_stone": "2024-08-29 02:31:26 +0000"
    },
    "done": true
  },
  "minecolonies:recipes/misc/blockhutcitizen": {
    "criteria": {
      "has_items": "2024-08-29 01:45:35 +0000"
    },
    "done": true
  },
  "minecraft:recipes/decorations/cartography_table": {
    "criteria": {
      "has_paper": "2024-08-29 01:45:40 +0000"
    },
    "done": true
  },
  "DataVersion": 3465
}